[{"channelId":"UCLpkseRtwlunqRNfqSrXfBA","publishedAt":"2018-11-27T05:10:16.000Z","title":"රට නම් දැන් අන්තිමයි ගන්න දෙයක් නැහැ- වගකියන්න ඕන  ජනපති","description":"Subscribe today for Latest News, Entertainments and Politics videos from Sri Lanka.\n#voicetube\n\nFollow on:\nOfficial website - https:\/\/www.voicetube.lk\nOfficial Facebook Page - https:\/\/www.facebook.com\/Voicetube.lk\/\nOfficial YouTube Channel - https:\/\/www.youtube.com\/c\/VoiceTubelk","viewCount":"71767","likeCount":"844","dislikeCount":"36","commentCount":"110","tags":["voice tube","Sri Lanka","LKA","Latest News","Politics videos"],"thumbnailUrl":"https:\/\/i.ytimg.com\/vi\/etNR3eEeb1M\/hqdefault.jpg","category":"P","sentiment":"P","comments":[{"id":"UgyE3s4P66EHu3S2pf54AaABAg","comment":"වෙල්ගම මහත්තගෙත් රාජයොගයක් පේනවා වගේ දැන් නමි","author":"Sanjaya Jayasiri","likeCount":0,"totalReplyCount":0,"publishedAt":"2019-10-06T13:01:09.000Z","replies":[]},{"id":"UgxUtW2HU0lVWuX2uip4AaABAg","comment":"TOO  TRUE","author":"yasa amara","likeCount":0,"totalReplyCount":0,"publishedAt":"2019-04-16T19:21:40.000Z","replies":[]},{"id":"Ugzv_rZ68PPBnvbTqhJ4AaABAg","comment":"Saththakinma oba hari. SB namathi boru kiyana pal hora deshapalanayen athuga damiya yutui.","author":"Shamini Fernanado","likeCount":0,"totalReplyCount":0,"publishedAt":"2018-12-26T16:18:28.000Z","replies":[]},{"id":"Ugw3dRHVEDSK4B3xmNp4AaABAg","comment":"oba tuma hariyatama  hari","author":"Nilani Sananayaka","likeCount":0,"totalReplyCount":0,"publishedAt":"2018-12-19T14:20:55.000Z","replies":[]},{"id":"Ugxogm4xiJ0eATL63jJ4AaABAg","comment":"Respect you welgama sir","author":"Kanchana Dilrukshi","likeCount":0,"totalReplyCount":0,"publishedAt":"2018-12-14T06:27:06.000Z","replies":[]},{"id":"UgwPa8AXcJxcWhyFmBd4AaABAg","comment":"welgamata jaya wewa","author":"Travel Srilanka","likeCount":0,"totalReplyCount":0,"publishedAt":"2018-12-12T16:12:53.000Z","replies":[]},{"id":"UgxASDRLM-983Vgkskl4AaABAg","comment":"APARADE BAHUTHARAYAK SIRISENAWA THORA GATHTHE JANAPATHI VIDIYATA ,,,WELGAMA MAHATHMAYA THORA NOGATHTHE AI? API MULINMA","author":"PEARL ANESTA","likeCount":0,"totalReplyCount":0,"publishedAt":"2018-12-09T19:00:48.000Z","replies":[]},{"id":"Ugx0OMwr70JMu6_LCKl4AaABAg","comment":"Rata anrhimai kiyanne thopi okkoma ekathu wela ratata kelewwe thopi thamai.","author":"Thusitha Ranasinghe","likeCount":0,"totalReplyCount":0,"publishedAt":"2018-12-09T11:08:13.000Z","replies":[]},{"id":"UgzhaqSXIWrE8KNg25h4AaABAg","comment":"Meyath horektamai 🐖🐖🐖","author":"Prabath Priyanga","likeCount":0,"totalReplyCount":0,"publishedAt":"2018-12-07T16:06:50.000Z","replies":[]},{"id":"UgxmbTYIVhptSg8oIrx4AaABAg","comment":"Walgama amati tumani kalin sita ganna spi nubata sapot","author":"Sanath Kumara Wijekoon","likeCount":0,"totalReplyCount":0,"publishedAt":"2018-12-07T13:03:22.000Z","replies":[]},{"id":"UgzlRBspiGG_VZ2zXnB4AaABAg","comment":"Well + gama  = welgama you r correct","author":"Wijesiri Muththettowage","likeCount":0,"totalReplyCount":0,"publishedAt":"2018-12-07T09:32:44.000Z","replies":[]},{"id":"UgzKfHFvgXbD1_JOeoJ4AaABAg","comment":"ඔබ තුමා කවදත් කෙලින් කතා කරපු කෙනෙක් ඔබ තුමාට ජය","author":"Daninder Degaldoruwa","likeCount":4,"totalReplyCount":0,"publishedAt":"2018-12-05T09:03:56.000Z","replies":[]},{"id":"UgwKmU03Bs49P_WB8UN4AaABAg","comment":"palayan yanna","author":"Kasun Chathuranga","likeCount":0,"totalReplyCount":0,"publishedAt":"2018-12-05T01:06:14.000Z","replies":[]},{"id":"UgxnR2x4fVGiUd55DKp4AaABAg","comment":"Well-done Sir, you are great. Keep it up!","author":"Martin Appuhamy","likeCount":0,"totalReplyCount":0,"publishedAt":"2018-12-04T15:41:15.000Z","replies":[]},{"id":"Ugy_YEKV8jeUsQuSBut4AaABAg","comment":"I'm a unp supporter but i like This man👏👏👏👏👏","author":"k. ravindran","likeCount":0,"totalReplyCount":0,"publishedAt":"2018-12-04T08:56:18.000Z","replies":[]},{"id":"UgxKKylAlr_C6fypoqJ4AaABAg","comment":"pisso kohomada theerana ganne ?","author":"cntcom wisdom","likeCount":0,"totalReplyCount":0,"publishedAt":"2018-12-04T01:55:06.000Z","replies":[]},{"id":"UgwAleJzHu2jpM4Akqd4AaABAg","comment":"MR WELGAMA SIR YOU ARE ABSOLUTELY CORTECT MS TOTALLY MENTALLY ILL PLEASE SEND HIM TO THE ANGODA","author":"Nihal Peiris","likeCount":0,"totalReplyCount":0,"publishedAt":"2018-12-03T16:44:59.000Z","replies":[]},{"id":"UgxTF4-kF7w7O0LA11R4AaABAg","comment":"Ala ala","author":"V8pula Amarathunga","likeCount":0,"totalReplyCount":0,"publishedAt":"2018-12-03T09:03:10.000Z","replies":[]},{"id":"UgxfGxmq0RxR3znbVD94AaABAg","comment":"Niyamai amathithumani","author":"kpg bandara","likeCount":0,"totalReplyCount":0,"publishedAt":"2018-12-03T04:26:14.000Z","replies":[]},{"id":"Ugzj8v-hyd_7KIXohTF4AaABAg","comment":"කොන්ද කෙලින් තියන් ඇත්ත කථාකරන එක ගැන් respect කරනව ඔබ තුමාට","author":"Chameera Alahakoon","likeCount":5,"totalReplyCount":0,"publishedAt":"2018-12-03T01:20:10.000Z","replies":[]},{"id":"UgyTSYa5tXoPQLShvIt4AaABAg","comment":"Obathuma thama agamathi wenda oni","author":"Chamara Herath","likeCount":0,"totalReplyCount":0,"publishedAt":"2018-12-02T17:50:12.000Z","replies":[]},{"id":"UgzHf8HL_ZFXLfWV4dl4AaABAg","comment":"ඇත්තටම ඹබ තමයි නියම ජේස්ටයා...ඹබ මෙ රටෙි ජාතික තලයට සුදුසු පුද්ගලයෙක්....!!ඇස්.බි .ගු හොටෙක් .....","author":"Chaminda Silva","likeCount":7,"totalReplyCount":0,"publishedAt":"2018-12-02T17:49:00.000Z","replies":[]},{"id":"UgzF6gMY559jJB1AQyd4AaABAg","comment":"ඔබ තුමා කවදත් කෙලින් කතා කරපු කෙනෙක් ඔබ තුමාට ජය","author":"Upul Abeysundera","likeCount":6,"totalReplyCount":0,"publishedAt":"2018-12-02T17:47:37.000Z","replies":[]},{"id":"UgyE460iJh5dOJQu3354AaABAg","comment":"Obata agamati venna baida????","author":"Sha Shahad","likeCount":0,"totalReplyCount":0,"publishedAt":"2018-12-02T16:35:50.000Z","replies":[]},{"id":"UgxGq7q8nWfXdwycE_N4AaABAg","comment":"Atta katava","author":"Sha Shahad","likeCount":0,"totalReplyCount":0,"publishedAt":"2018-12-02T16:35:17.000Z","replies":[]},{"id":"UgzANzYbgf7MXymKwex4AaABAg","comment":"ආන්ඩුවෙ බහුතරය නොවේ  ජනතාවගෙ බහුතරය තිබිය යුතුයි .","author":"Lata Anawala","likeCount":1,"totalReplyCount":0,"publishedAt":"2018-12-02T16:26:25.000Z","replies":[]},{"id":"UgwVNRw3oft9PNHRd9h4AaABAg","comment":"මේ මිනිහ සිටිනතුරා විවේචනය එලවා දමන්න  පක්ෂෙ සෝදා පාළුවෙන්","author":"Karunaratne Wijeratne","likeCount":0,"totalReplyCount":0,"publishedAt":"2018-12-02T16:25:05.000Z","replies":[]},{"id":"Ugxb-2AFuJmZx5Svzwh4AaABAg","comment":"Obatuma konda කෙලින් tiyagena kata කරන eka gana godak satutui","author":"Asela Madhusanka","likeCount":0,"totalReplyCount":0,"publishedAt":"2018-12-02T16:00:15.000Z","replies":[]},{"id":"UgxliQF7jv4yDVJCeYV4AaABAg","comment":"Hiru Itn ජාතික දෙරණ ආණ්ඩුවට kade yana gon pakayoo daapiyau menna me vedios news walata","author":"Roshan Bandara","likeCount":1,"totalReplyCount":1,"publishedAt":"2018-12-02T15:54:37.000Z","replies":[{"parentId":"UgxliQF7jv4yDVJCeYV4AaABAg","authorDisplayName":"Saminda Fernando","replyComment":"A","publishedAt":"2019-08-10T13:52:31.000Z","likeCount":0}]},{"id":"UgwIDu1Zd-CNCQnEX7d4AaABAg","comment":"Aka aeththa serama gedara yawanna thamayi ona","author":"Sakunthala Kkumari","likeCount":0,"totalReplyCount":0,"publishedAt":"2018-12-02T13:33:49.000Z","replies":[]},{"id":"Ugx-rcVv9Yq8nyPZAJh4AaABAg","comment":"Rate ninisunta awashaya maha jandaya misak thunen deka nemethunen deka ona aemathilata","author":"Sakunthala Kkumari","likeCount":0,"totalReplyCount":0,"publishedAt":"2018-12-02T13:33:22.000Z","replies":[]},{"id":"UgwTvLC_lj5ARAA-QwF4AaABAg","comment":"Obathuma itha Honda desapalakayeki. Jayawewa \nMinissu chandaya diyauththe oba wage ayatai.","author":"Kumuduni Gunasekara","likeCount":0,"totalReplyCount":0,"publishedAt":"2018-12-02T13:22:55.000Z","replies":[]},{"id":"UgzF40WO7hhKcf89Oat4AaABAg","comment":"Ana pako","author":"THARANGA PARANAGAMA","likeCount":0,"totalReplyCount":0,"publishedAt":"2018-12-02T13:01:15.000Z","replies":[]},{"id":"Ugw_dydzQhFB2m_6pDl4AaABAg","comment":"Mahinda wahallunta obe me katawa dirawann","author":"nadu katu","likeCount":0,"totalReplyCount":0,"publishedAt":"2018-12-02T13:00:43.000Z","replies":[]},{"id":"Ugz3KaL6uZwdSvObl3R4AaABAg","comment":"https:\/\/www.youtube.com\/channel\/UC8ivFmZmVDZgRYldF_pstVQ?view_as=subscriber","author":"HARITHA TV","likeCount":0,"totalReplyCount":0,"publishedAt":"2018-12-02T12:57:46.000Z","replies":[]},{"id":"UgxJriptWkU8NZG8Zux4AaABAg","comment":"Kawadahari.janadipathi","author":"Jayantha Jayantha","likeCount":0,"totalReplyCount":0,"publishedAt":"2018-12-02T12:57:19.000Z","replies":[]},{"id":"Ugyz8NcEGQZfByyTtsJ4AaABAg","comment":"මූටනම් මොලේ නෑමයි කියමුකො ඊට වඩා හපන් මේ වගේ උපන්ගෙයි වලත්තයෙක්ගෙන් ප්‍රශ්න අහන්නෙ.","author":"Minoka Senasinghe De Silva","likeCount":0,"totalReplyCount":0,"publishedAt":"2018-12-02T12:30:28.000Z","replies":[]},{"id":"UgyNuPKu_0etYcPhKup4AaABAg","comment":"Mr lokka guli kanna mechchara dakshai kiyala api danne ne,\n\nMr ge baleta thiyana kadara kanai..\nGotata place eka yai kiyana bayata thamai mr guliya kewe...\n\nDan thiyenne vipaksheta yana eka,","author":"Rocxx Max","likeCount":0,"totalReplyCount":0,"publishedAt":"2018-12-02T12:09:00.000Z","replies":[]},{"id":"UgwQZazeMB6J7HDCbWZ4AaABAg","comment":"Good job","author":"Pas Chinthaka","likeCount":0,"totalReplyCount":0,"publishedAt":"2018-12-02T10:15:33.000Z","replies":[]},{"id":"UgzinjjG3Uzg69IkY2Z4AaABAg","comment":"Ela","author":"Sameera Sampath","likeCount":0,"totalReplyCount":0,"publishedAt":"2018-12-02T04:13:03.000Z","replies":[]},{"id":"UgzeiXcQDfvK8CmcXst4AaABAg","comment":"එස්බී කියන්නෙ, දවසක් උගෙ අම්ම වැසිකිලි ගිය දවසක එතනදි හම්බ වුනු සක්කිලියෙක්. ඉපදුන දවසෙ ඉදලම ගදයි. කටත් කක්කුස්සියක් වගෙයි. ඌ අංක 1.  එතකොට වැසිකිලි  අංක 2  තමයි සුකරවංස. අංක 3 ගොබ්බංපිල සක්කිලියා. අංක 4 බන්දුල සුනඛයා.5 තමයි ඩලසය  6  දිනේසය 7 වාසුවා.","author":"Anandha Amitha","likeCount":8,"totalReplyCount":0,"publishedAt":"2018-12-02T03:44:09.000Z","replies":[]},{"id":"UgyF0fj9I-e4sWfgv9l4AaABAg","comment":"වෙල්ගම අගමැතිකමට සුදුස්සෙක්.පක්ෂ ගැන නොසලකා මමනම් සහාය දෙනව. සුභ පතනව.අපක්ෂපාති මිනිසෙක්. ජය වේවා.","author":"Anandha Amitha","likeCount":5,"totalReplyCount":0,"publishedAt":"2018-12-02T03:38:19.000Z","replies":[]},{"id":"UgwpFJvXJdt6Nlh5xrp4AaABAg","comment":"රාජපක්ෂයලා ඕන බලය.. එය හබකෙන් බැරිනම් කෙමනෙන් හරි...\nඑයාලට ප්‍රතිපත්ති වැදගත් නැහැ. සදාචාරය වැදගත් නැහැ. රටේ ආර්ථික වැදගත් නැහැ. මහින්ද වට කරන් ඉන්න හයිනාවන් රෑන හිතා ඉන්නේ රටේ මිනිස්සු ගොන්නු කියල. ඔබතුමා කියන ඒව එයාල අහන්නේ නැහැ..\nගොබ්බන්පිළලා , සූකරවංශලා , සිහින අගමැති නාකි දිනේශ් , මෙයාලා මහින්දට කෙලෙවලා ඉවරයි...","author":"Martin Luther","likeCount":5,"totalReplyCount":2,"publishedAt":"2018-12-02T02:52:56.000Z","replies":[{"parentId":"UgwpFJvXJdt6Nlh5xrp4AaABAg","authorDisplayName":"Martin Luther","replyComment":"@Sun Shine \n👍...\nමේවා ඇස්පනාපිටම පෙනෙන සරලම සරල සත්‍යය..","publishedAt":"2018-12-05T04:18:51.000Z","likeCount":0},{"parentId":"UgwpFJvXJdt6Nlh5xrp4AaABAg","authorDisplayName":"Sun Shine","replyComment":"Martin Luther so true","publishedAt":"2018-12-02T15:00:50.000Z","likeCount":0}]},{"id":"UgygUqbxD3vhvBs88Ld4AaABAg","comment":"Jvp & ඔබ තුමා වැනි වැදගත් මිනිස්සු ඉන්න යන්න epa","author":"sumith priyantha","likeCount":5,"totalReplyCount":0,"publishedAt":"2018-12-02T01:47:05.000Z","replies":[]},{"id":"UgzqZ3kWbaaRnOFm-7h4AaABAg","comment":"Sb අවජාතක sakkiliyek කාලකන්නි","author":"sumith priyantha","likeCount":4,"totalReplyCount":0,"publishedAt":"2018-12-02T01:42:34.000Z","replies":[]},{"id":"Ugwj01edwXqoPVPzJFx4AaABAg","comment":"Sri you are a honesty Person. Sri you keep IT Up your respect.","author":"Yogarasa Sundaram","likeCount":0,"totalReplyCount":0,"publishedAt":"2018-12-01T23:38:11.000Z","replies":[]},{"id":"UgzLiLnKQXyjss0l9dB4AaABAg","comment":"Jaya wewa oba thumata.","author":"Nilanka Subasini","likeCount":0,"totalReplyCount":0,"publishedAt":"2018-12-01T21:08:05.000Z","replies":[]},{"id":"UgwHPAhi3nuiJLfEJ0h4AaABAg","comment":"kohomada nalangnagee  saskrutiya  eelnaga   paeniaappaya vageee  ponuthew daka athe mevage ponnu nodakkaya ekayi hutthioo san skruthiya???","author":"roshan abewickrama","likeCount":0,"totalReplyCount":0,"publishedAt":"2018-12-01T19:19:30.000Z","replies":[]},{"id":"UgzCNN6PHfsMBT0-2H54AaABAg","comment":"Niyama miniha kelin katha karana konda panathina","author":"Asiri Asiri","likeCount":0,"totalReplyCount":0,"publishedAt":"2018-12-01T18:23:07.000Z","replies":[]},{"id":"UgwrTpDg553Zx6_xhEF4AaABAg","comment":"Dan me Anduwata anuwa Parliament eka wasa damiya uthui.       Welgama u are great.","author":"Chami Pingamage","likeCount":1,"totalReplyCount":0,"publishedAt":"2018-12-01T18:08:09.000Z","replies":[]},{"id":"UgywYgc2RFktNwHq7u54AaABAg","comment":"Na oba thumala waga kalin katha karana wada karana aka hitiyada kamak na ara 16 kalliyata gahala pannanna ona","author":"Qumari Fh","likeCount":0,"totalReplyCount":0,"publishedAt":"2018-12-01T17:35:39.000Z","replies":[]},{"id":"UgzCta9HvOwZQ8dDr4l4AaABAg","comment":"ඇත්තම ඇත්තයි s.b කියන්නනෙ රටට  පිලිලයක්  බොරුකාරයා  එලවාදැමියයුතුයි","author":"calista fernando","likeCount":15,"totalReplyCount":3,"publishedAt":"2018-12-01T16:37:48.000Z","replies":[{"parentId":"UgzCta9HvOwZQ8dDr4l4AaABAg","authorDisplayName":"Ananda Ukwattage","replyComment":"Penne nadda s.b kiyana ekage phuppahi hinawa.prasna ahana serama gonnune","publishedAt":"2019-07-27T16:31:20.000Z","likeCount":0},{"parentId":"UgzCta9HvOwZQ8dDr4l4AaABAg","authorDisplayName":"Ananda Ukwattage","replyComment":"Anthimata serama  eka walle horu tika ekathuwei.minissu rawatei","publishedAt":"2019-07-27T16:29:28.000Z","likeCount":0},{"parentId":"UgzCta9HvOwZQ8dDr4l4AaABAg","authorDisplayName":"Anandha Amitha","replyComment":"calista fernando හිරේ ගිය එකෙක්, පැරදුනු එකෙක්,  ආන්ඩුවට ගත්ත බූරුවා දැනගන්න එපායැ.","publishedAt":"2018-12-08T03:43:12.000Z","likeCount":0}]},{"id":"Ugy4-W09N8r24SI9TxV4AaABAg","comment":"my3 ammta hukwanna oni ponna pala","author":"amila Sige","likeCount":0,"totalReplyCount":0,"publishedAt":"2018-12-01T12:50:40.000Z","replies":[]},{"id":"UgwEw8yYyPDKPmIPWIZ4AaABAg","comment":"හරියටම.   හරි. ඔබ. තුමගේ .කතව. ඔබට . ජයම. වෙිවා   ඔබ. අවන්ක. කතව .","author":"Tereza Ter","likeCount":13,"totalReplyCount":0,"publishedAt":"2018-12-01T12:17:02.000Z","replies":[]},{"id":"UgzkOhxBgdPuWxrFGOV4AaABAg","comment":"ජනපතිකමට උවත් සුදුසු කසේරුකාවක් අැති සැබෑමිනිසා.","author":"nimal shantha","likeCount":13,"totalReplyCount":1,"publishedAt":"2018-12-01T09:15:10.000Z","replies":[{"parentId":"UgzkOhxBgdPuWxrFGOV4AaABAg","authorDisplayName":"Sanju Presad","replyComment":"Wenne","publishedAt":"2018-12-16T13:06:09.000Z","likeCount":0}]},{"id":"Ugwy7ws5Y1Ohpptg9et4AaABAg","comment":"your right you speak the truth.","author":"fauz thaliffdeen","likeCount":0,"totalReplyCount":0,"publishedAt":"2018-12-01T09:00:32.000Z","replies":[]},{"id":"UgyqXBEaynN2_01jMNV4AaABAg","comment":"Atta obatuma kiyanne","author":"Sujani Champika","likeCount":0,"totalReplyCount":0,"publishedAt":"2018-12-01T06:33:03.000Z","replies":[]},{"id":"Ugz7iivYotlRNroP0ux4AaABAg","comment":"Mahinda nowa  obai  priministar","author":"Rohan Divisekara","likeCount":11,"totalReplyCount":0,"publishedAt":"2018-12-01T06:05:46.000Z","replies":[]},{"id":"Ugzwxb08oOSr1gvd8C94AaABAg","comment":"Ubath dolar aragatthada.rata vinasa wela iwaraithopi ekekutawath chande dennana hora hattha.tho ekek wath rata adare na.thope madi thada kara gannawa.225 gedara pala","author":"Panadura Zoysa","likeCount":0,"totalReplyCount":1,"publishedAt":"2018-12-01T06:02:32.000Z","replies":[{"parentId":"Ugzwxb08oOSr1gvd8C94AaABAg","authorDisplayName":"Chandani Edirisinghe","replyComment":"Obathuma. Nam.  Pudumai.  Oya. Pakshe. Inawada,   keyala.  Ai.  Inna. Aneth.  Gon. Ralata.  Therenne.   Nadda. Me.  Asadarane.  Oba.  Thuma. Anna.  Agamathei.  Kamata. Apita. Ona. Oya wage.  Menissu","publishedAt":"2018-12-03T01:53:50.000Z","likeCount":0}]},{"id":"UgyrNXn6abe-EEHozSp4AaABAg","comment":"you  are  a correct  person. best wishes","author":"Sunita Jayasinghe","likeCount":0,"totalReplyCount":0,"publishedAt":"2018-12-01T04:16:51.000Z","replies":[]},{"id":"UgyBjr65DvU2oQcEbKx4AaABAg","comment":"වෙල්ගම මහත්තයෝ ඇත්ත කතාව. හිටං ලනු කෑවෙ not only SB., bt ඩිලාන් සුසිල් වාසු විමල් ගම්මා පවිත්‍රා අරුන්දික දිනේෂ් මාල කඩා ඩලස් ජොන්ටා මහින්ද...etc etc","author":"Gerard Adikaram","likeCount":17,"totalReplyCount":0,"publishedAt":"2018-12-01T04:16:19.000Z","replies":[]},{"id":"UgxvpfzivcZ1gd4aC3p4AaABAg","comment":"Anna niyama janathaa  puthrayek  ...","author":"always calm","likeCount":0,"totalReplyCount":0,"publishedAt":"2018-12-01T03:50:42.000Z","replies":[]},{"id":"UgyEJyLoxV3QqkXQaRN4AaABAg","comment":"well said.!!!","author":"Harini Fonseka","likeCount":1,"totalReplyCount":0,"publishedAt":"2018-11-30T19:37:25.000Z","replies":[]},{"id":"Ugw24-XAjITN1pnFG6t4AaABAg","comment":"Edithara nirbeetha naayakayek...Our next president","author":"Adam Lebbe Amanulla","likeCount":0,"totalReplyCount":0,"publishedAt":"2018-11-30T10:03:56.000Z","replies":[]},{"id":"UgymsqQvKmbrybAFIIV4AaABAg","comment":"Welgama oba thuma harima sadarana pudgalyek. Mata hithanawa obath Ranil mahathaya ekka deshapalanayata ekathu wunoth rate obata Honda piliganeemak athiwai. Oba aththa katha karana kenek nisa.\nAwoth Hondai kiyala hithanawa. Mage pawthgalika Adahasak!  Nirbeethawa thirana thindu ganna kenek washayen mama oba thumata suba pathanawa. Obathumata therenawa neda Maithripala borukarayek. Sadarana kenek nam bahutharayak thibena Ranilta Agamathi kama deela rata paalanaya geniyanna ona\nRajapaksa Agamathi  kireemata kisima balayak naha. moda pala ratema peachan wela iwarai. . Lokayeth api  diha balagena iinnawa ape rate Ada siddawena  deshapalanayen ratama sauthu wela iwarai.   Obathuma U.N.P. ta awoth mulu ratama obawa piliganiy! Manda oba thuma sadarana katha karana nisa. Mama obathuma ithama gaurawa karanawa. Good luck!","author":"Mohammed Muzaahir","likeCount":0,"totalReplyCount":0,"publishedAt":"2018-11-27T20:16:06.000Z","replies":[]},{"id":"UgyKyk7gIXJbEw5Wn0J4AaABAg","comment":"Oba tumata ma hisa nama gaurava karanava.","author":"Soso Foufou","likeCount":2,"totalReplyCount":0,"publishedAt":"2018-11-27T19:21:49.000Z","replies":[]},{"id":"UgwEXlCFyOvOAww5VYZ4AaABAg","comment":"හොඳයි නම් හොඳයි කිවයුතුයි .    හරි කතාව.....","author":"Bob මැක්","likeCount":11,"totalReplyCount":0,"publishedAt":"2018-11-27T18:35:10.000Z","replies":[]},{"id":"UgzAWXS8zA5l7hswmCl4AaABAg","comment":"ඔබතුමා දන්නේ නැද්ද 122 පෙන්නපු විදිය ාධ්‍යයට කතාකරන්නේ කටින්ද පුකෙන්ද ලැජ්ජයි වෙල්ගම ඔබතුමා කිව්වා නේද වමේ කියලා පස්ස පැත්තෙ වමේ වෙන්න ඇති","author":"Kumara Sisira","likeCount":0,"totalReplyCount":2,"publishedAt":"2018-11-27T17:23:19.000Z","replies":[{"parentId":"UgzAWXS8zA5l7hswmCl4AaABAg","authorDisplayName":"Indrani Nanayakkara","replyComment":"welgama obata kaseruķàwak thiyenawa aththa athisatiyen daķinna bayà nathiwa pràkasha karanna balayata kàadara raja pawlata ķath àdina wahal manasikkath àthi ģottanta yatharþhaya wath ganan hilawwath therenne ñaha!!!","publishedAt":"2019-05-17T13:02:05.000Z","likeCount":0},{"parentId":"UgzAWXS8zA5l7hswmCl4AaABAg","authorDisplayName":"Nevil Kumara","replyComment":"Uba mahindata puka dena akek neada..yako etta tearum ganin ..a manussaya keyanadea ettaa neweyda..gon pakaya..","publishedAt":"2018-11-30T12:47:28.000Z","likeCount":2}]},{"id":"Ugy4xnyG_ZapECQz1O54AaABAg","comment":"ඔබතුමාළුස් බී සමග තිබෙන පලහිලව්ව පෞද්ගලිකව විසදගන්න 16 කල්ලිය කියලා ඔබතුමාලා නේද එකතු වෙලා හිටියේ දැන් මොකද තරහා වෙලා ාධ්‍යයට නුවමනා කතා හසුරවන්නේ එපා තැනක ඔබ කියනවා මහින්ද රාජපක්ෂ අගමැති කැමැතියි කියලා තැනක ඔබ කියනවා රට ඉවරයි කියලා කතා දෙකක් නේද ලැජ්ජයි ඇමතිතුමා කරුණාකර ඔබ පාර්ලිමේන්තු නොවෙනවා නම් උඹ වගේ අය ගෙදර ඉන්න එක තමයි ගොඩක් හොද එක එක මත කියලා video ්‍රදර්ශනය කරලා නිකං මහජනතාවගෙන් කැපෙන්න එපා නම්බුනාම පිටින් ගෙදර ඉන්න සුදුසුකම ඒකයි","author":"Kumara Sisira","likeCount":0,"totalReplyCount":0,"publishedAt":"2018-11-27T17:22:01.000Z","replies":[]},{"id":"UgxdCp2SJzpQzMX6knt4AaABAg","comment":"👍👍👍","author":"Shakoor Abdul","likeCount":3,"totalReplyCount":0,"publishedAt":"2018-11-27T15:34:54.000Z","replies":[]},{"id":"Ugwqetw8sltE6n8xhz54AaABAg","comment":"ඔබ.තුමා.👍","author":"Yarakaruna kahada","likeCount":11,"totalReplyCount":1,"publishedAt":"2018-11-27T13:07:22.000Z","replies":[{"parentId":"Ugwqetw8sltE6n8xhz54AaABAg","authorDisplayName":"Malith Livera","replyComment":"Yarakaruna hi","publishedAt":"2018-12-03T11:00:00.000Z","likeCount":0}]},{"id":"UgyD_do4RwpMRoAqiB14AaABAg","comment":"JANADIPATIGE   KAN BIRI WELA  AHENNE NAHA ,,,,,,,, DANNE NADDA  AMATHI THUMANI","author":"thushari siddi arachchige","likeCount":2,"totalReplyCount":0,"publishedAt":"2018-11-27T12:07:34.000Z","replies":[]},{"id":"UgzRI_BlOalKgt6jSVt4AaABAg","comment":"වග කියන්න ඕනේ ජනාධිපති තුමා. Obe තුමාට බුදු සරණයි .","author":"Helen Deepthi","likeCount":18,"totalReplyCount":0,"publishedAt":"2018-11-27T11:02:06.000Z","replies":[]},{"id":"UgwmSV1UDGN5NfD30FN4AaABAg","comment":"ඔබතුමාට thiyana mole ජනපති narumayata ne aka nisa a yakata කවුරු කිව්වත් wedak ne me wela thiyana de dakina balana one babekuta therenawa weredda karala katawahagena enne ජනපති sira කියලා serama tika kotawala nariyek wage hengila balan ennawa 😂","author":"himasha rayani","likeCount":7,"totalReplyCount":1,"publishedAt":"2018-11-27T10:22:40.000Z","replies":[{"parentId":"UgwmSV1UDGN5NfD30FN4AaABAg","authorDisplayName":"Damayanthi Renuka","replyComment":"lassana lanka niyamaI hoda manussaya","publishedAt":"2018-12-01T18:37:24.000Z","likeCount":0}]},{"id":"Ugwm4K3wJZhKaSk_gyF4AaABAg","comment":"Oba thuma kalin minihek","author":"Upali Sarath","likeCount":2,"totalReplyCount":0,"publishedAt":"2018-11-27T10:13:12.000Z","replies":[]},{"id":"Ugw-a9Ks3DUeFWbO4Mh4AaABAg","comment":"ඉතාමත් නිවැරැදි ප්‍රකාශය ,, ඔබට ජය","author":"Nikawaththa nikawaththa","likeCount":25,"totalReplyCount":0,"publishedAt":"2018-11-27T10:03:36.000Z","replies":[]},{"id":"Ugy3iI1fMpSSYLSDfrF4AaABAg","comment":"Oba thumata thiyana mole. Ara gon sirisenata na. Sira pissek","author":"rohana nawarathna","likeCount":10,"totalReplyCount":0,"publishedAt":"2018-11-27T09:17:00.000Z","replies":[]},{"id":"UgzpbtNfJKN6HTcmUGV4AaABAg","comment":"දැන් රට අන්තිමයි කියන්නේ හොර අගමැතිට වඩා හිටපු අගමැතිගේ කාලය හොදයි කියන එක නොවේද ?","author":"B A sanje","likeCount":16,"totalReplyCount":3,"publishedAt":"2018-11-27T08:56:32.000Z","replies":[{"parentId":"UgzpbtNfJKN6HTcmUGV4AaABAg","authorDisplayName":"Sumanedasa Lokusooriya","replyComment":"Hlndl best songs","publishedAt":"2018-12-09T08:17:56.000Z","likeCount":0},{"parentId":"UgzpbtNfJKN6HTcmUGV4AaABAg","authorDisplayName":"Sumanedasa Lokusooriya","replyComment":"Www.youtube","publishedAt":"2018-12-09T08:15:47.000Z","likeCount":0},{"parentId":"UgzpbtNfJKN6HTcmUGV4AaABAg","authorDisplayName":"akila kumara","replyComment":"Paiya හොඳයි ranil ponnaya","publishedAt":"2018-12-03T16:33:15.000Z","likeCount":0}]},{"id":"UgwGbyforws3rBIUApt4AaABAg","comment":"bora diye malu bama","author":"Udaya Nanditha","likeCount":0,"totalReplyCount":2,"publishedAt":"2018-11-27T08:46:41.000Z","replies":[{"parentId":"UgwGbyforws3rBIUApt4AaABAg","authorDisplayName":"Adnan Mohamed","replyComment":"Jayawewa","publishedAt":"2018-12-21T16:11:30.000Z","likeCount":0},{"parentId":"UgwGbyforws3rBIUApt4AaABAg","authorDisplayName":"Lakshman Mapalagama","replyComment":"Mr walgam obaga parakasayata awankawa sathutu wanawa","publishedAt":"2018-11-27T15:44:03.000Z","likeCount":0}]},{"id":"UgyN4606-oXHI1R5I0R4AaABAg","comment":"👍👍","author":"Mery Ranjith","likeCount":3,"totalReplyCount":0,"publishedAt":"2018-11-27T08:17:17.000Z","replies":[]},{"id":"UgyI66ewxrdGRhYFaah4AaABAg","comment":"ඉතාමත් නිවැරැදි ප්‍රකාශය ,, ඔබට ජය .","author":"Marki bm","likeCount":17,"totalReplyCount":0,"publishedAt":"2018-11-27T08:15:28.000Z","replies":[]},{"id":"UgzSw59d7nSJ0T_Pzcp4AaABAg","comment":"Please form a team ppl like u n pressure both the main parties for the goodwill of the country n ppl\nGood bless u","author":"somasiri rajapaksha","likeCount":5,"totalReplyCount":0,"publishedAt":"2018-11-27T07:26:02.000Z","replies":[]},{"id":"UgwKf748HxOzxF-HRyN4AaABAg","comment":"Hemathissema aththa katha karanna ekata garukaranawa","author":"Nimal Chandrasiri","likeCount":4,"totalReplyCount":0,"publishedAt":"2018-11-27T07:12:47.000Z","replies":[]},{"id":"UgwCSRpBHucvm90I7tB4AaABAg","comment":"Oba tumala wage ayata tama me rata hadanna pulun","author":"Kumara Bandara","likeCount":11,"totalReplyCount":0,"publishedAt":"2018-11-27T06:47:08.000Z","replies":[]},{"id":"UgwAGI1L22CbHzVSH4N4AaABAg","comment":"Obathuma nam mahathma gathi thiyana kenek obathumata dirga kalayak parlimenthuwe inna labewa dirgayusha labewa","author":"Sriyana Sriyana","likeCount":6,"totalReplyCount":0,"publishedAt":"2018-11-27T06:35:55.000Z","replies":[]},{"id":"UgxmMgfE268IfnfaUz94AaABAg","comment":"Pata desha palane nathiwa age kala uthu porak","author":"aruna lanka","likeCount":7,"totalReplyCount":0,"publishedAt":"2018-11-27T06:23:46.000Z","replies":[]},{"id":"Ugwta1gUs1kipMz6KFV4AaABAg","comment":"Obata hoda anagathayak  tiyenawa desha palane oya vidiya tama giyoth thanks","author":"aruna lanka","likeCount":5,"totalReplyCount":0,"publishedAt":"2018-11-27T06:22:55.000Z","replies":[]},{"id":"UgwCGAhm9r52_MRYmy94AaABAg","comment":"ඔබ  තුමා  ඉතා මත් නිවැරැදි","author":"Malki Bandaranayake","likeCount":23,"totalReplyCount":0,"publishedAt":"2018-11-27T06:10:04.000Z","replies":[]},{"id":"UgyvUo3e9CR4VBmXjeN4AaABAg","comment":"Me welawe bala lobaya nathiwa rata gana sithana ekama pora","author":"aruna lanka","likeCount":2,"totalReplyCount":0,"publishedAt":"2018-11-27T06:08:38.000Z","replies":[]},{"id":"UgwHUUgaoEtKcBY0apx4AaABAg","comment":"Yes","author":"aruna lanka","likeCount":4,"totalReplyCount":0,"publishedAt":"2018-11-27T06:07:16.000Z","replies":[]},{"id":"UgwJSMpGoBJa9c5FkzJ4AaABAg","comment":"Obata terena de joker nayakata terenne na","author":"aruna lanka","likeCount":2,"totalReplyCount":0,"publishedAt":"2018-11-27T06:06:59.000Z","replies":[]},{"id":"UgzbVKtxn_9MjF6j3hV4AaABAg","comment":"ඇත්ත  ඔබතුමා  ගෙ කතාව","author":"Mohamed","likeCount":30,"totalReplyCount":0,"publishedAt":"2018-11-27T06:04:48.000Z","replies":[]},{"id":"UgzyYp8C7x4DxoLNz0d4AaABAg","comment":"Yes","author":"Mohammad Shiron","likeCount":3,"totalReplyCount":0,"publishedAt":"2018-11-27T05:43:59.000Z","replies":[]}]}]