[{"channelId":"UCGyMpmlNZ-CLbW1GmUdIBKw","publishedAt":"2020-01-27T13:49:28.000Z","title":"මෙන්න නිදිවදින වොල්කාගේ ලීක් වූ වීඩියෝව..","description":"යාළුවනේ වීඩියෝව නරඹන ඔයාල අමතක නොකර අපේ චැනල් එකත් Subscribe කරන්න.ඒ වගේම අපේ වීඩියෝ මුලින්ම නැරඹීම සඳහා Subscribe බටන් එකට දකුණු පැත්තෙන් තියෙන බෙල් Icon එකත් අමතක නොකරම Click කරන්න හොඳේ..❤️","viewCount":"53956","likeCount":"266","dislikeCount":"128","commentCount":"223","thumbnailUrl":"https:\/\/i.ytimg.com\/vi\/K1_V415THuo\/hqdefault.jpg","category":"SG","sentiment":"N","comments":[{"id":"Ugxs9uztjvpvna9ZQSJ4AaABAg","comment":"Uba hukapan paratawesiye thuknodakin thopiwage un","author":"Samantha Kumara","likeCount":0,"totalReplyCount":0,"publishedAt":"2020-02-17T08:04:36.000Z","replies":[]},{"id":"UgzOwxxUw8WXWhnfweF4AaABAg","comment":"උඹ කාත් එක්ක වුනත් නිදිය ගත්තට කමක් නෑ.....යකෝ තාත්තලා අපි වෙනුවෙන් මොනවද නොකෙරැවෙ.....කාලකන්නි ගෑණි....😭","author":"Shehan liyanage","likeCount":0,"totalReplyCount":0,"publishedAt":"2020-02-11T13:29:36.000Z","replies":[]},{"id":"UgzZ-eIehvK9AWVi2Rp4AaABAg","comment":"Me chenal karanekkenage leak vechchi video ekak please","author":"Mohamed Arsath","likeCount":0,"totalReplyCount":0,"publishedAt":"2020-02-07T08:44:44.000Z","replies":[]},{"id":"UgxCED-C8Z8NEVGEboN4AaABAg","comment":"ඔක ලික් උන එකක් නෙවීඊ පෙන්න දාපු ekakk","author":"Sanjana Dulanji","likeCount":0,"totalReplyCount":0,"publishedAt":"2020-02-05T16:25:06.000Z","replies":[]},{"id":"UgzksgZH7TY31NIZcHd4AaABAg","comment":"වෝල්කා  මොනවා කරත් මට ප්‍රශ්නයක් නැ එත් අම්මා  තාත්තාට වැඩිය වටින කෙනෙක් මේ ලොකෙ නැ බැල්ලියෙ ඔය මිනිහාත් දලා ගියදට ඔයට ඉන්නෙ ඔයගෙ අම්මා තාත්තා විතරයි ඔයට ඔය පාවම ඇති","author":"Chamila Chamila","likeCount":0,"totalReplyCount":0,"publishedAt":"2020-02-02T19:54:35.000Z","replies":[]},{"id":"UgzDAtpCupWHV9afsfF4AaABAg","comment":"Nodakin patta paduru dhapadura 🐕.ganu sata","author":"Aberathna Fonseka","likeCount":0,"totalReplyCount":0,"publishedAt":"2020-02-02T10:59:48.000Z","replies":[]},{"id":"UgzRMwoyIbNdvtpaPtB4AaABAg","comment":"මේක නුබගේ තාත්තා අැහුවනම් අපරාදේ කියයි නමුත් නැ අවශ්‍ය නැ.","author":"Nimal Jayananda","likeCount":0,"totalReplyCount":0,"publishedAt":"2020-02-02T07:46:11.000Z","replies":[]},{"id":"UgzYwTyzgGIOSih0QmZ4AaABAg","comment":"apita  wadak  na  moka akka  nidiwadunat.apitanam damwpiyo taram kawrut  watinna  na.makige damwpiyo maka dakala mari  mari upadibawa ati too wage akak jataka kalata","author":"gayan sameera","likeCount":0,"totalReplyCount":0,"publishedAt":"2020-02-01T16:19:27.000Z","replies":[]},{"id":"UgzzOKTPRpzXc_1JLmV4AaABAg","comment":"Me rangapana wesiyanta kulappuwa hedunama Thaththa aduranneth be.miniha aduranneth ne.anika ithin aduraganna baritharam mekilata minissu   keedenek Ekka budiyanawada wesiyo","author":"Sandra Kur","likeCount":0,"totalReplyCount":0,"publishedAt":"2020-01-31T21:57:19.000Z","replies":[]},{"id":"UgwHx76HsEBrknABKN94AaABAg","comment":"Maga daviyo amma .appchchi","author":"Priyanka Vijayvardhana","likeCount":0,"totalReplyCount":0,"publishedAt":"2020-01-31T20:06:21.000Z","replies":[]},{"id":"UgyV1c93uwg5k4AUrRJ4AaABAg","comment":"තාත්ත කවුද කියල දැකලවත් නැතුව ඇති ඒකයි තාත්ත කියන උතුම් මනුස්සයට ගරහන්නෙ","author":"Kumara Rohan","likeCount":0,"totalReplyCount":0,"publishedAt":"2020-01-31T17:05:15.000Z","replies":[]},{"id":"UgwdVgxi6AyUKS-QOEN4AaABAg","comment":"වොල්ගා 😂වල්ගා 😂","author":"ඉෂාර ලොකුගමගේ","likeCount":0,"totalReplyCount":0,"publishedAt":"2020-01-31T16:03:55.000Z","replies":[]},{"id":"Ugy_5PHIEr-_Ac7ZCHF4AaABAg","comment":"මට නම්  මගේ තාත්තා  තරමි වටින  කෙනෙක් මෙි ලෝකෙ නැ","author":"Indu Nisansala","likeCount":0,"totalReplyCount":0,"publishedAt":"2020-01-31T16:02:46.000Z","replies":[]},{"id":"UgzbDFC45hRVUMFnWPJ4AaABAg","comment":"අනේ උඹල ඔක්කොම එකයි","author":"Darmakirthi Jayasundara","likeCount":0,"totalReplyCount":0,"publishedAt":"2020-01-31T14:41:45.000Z","replies":[]},{"id":"Ugw2X_e2oKlltdefYpV4AaABAg","comment":"Woow.supiri.suba anaagathayak dennatama.","author":"nimali Al","likeCount":0,"totalReplyCount":0,"publishedAt":"2020-01-31T11:48:11.000Z","replies":[]},{"id":"UgxmJ_WJEgkZL6nXAxl4AaABAg","comment":"🤭තාත්තා නැ මේකිට අවඡාතකායි එකයි😒","author":"Viraj Wickramarathna","likeCount":0,"totalReplyCount":0,"publishedAt":"2020-01-31T11:35:20.000Z","replies":[]},{"id":"UgwUyLpZKGyLi47F80t4AaABAg","comment":"Wolga newei walga kiyala danna thibune.","author":"Chamod Sheshan","likeCount":0,"totalReplyCount":0,"publishedAt":"2020-01-31T11:24:21.000Z","replies":[]},{"id":"UgxYPIVWpEul9rmivaJ4AaABAg","comment":"Ane jara genu gena mona kathada..Adum maru karanawa wage මිනිස්සු  maru karanawa ...","author":"Tharushika Malshani","likeCount":0,"totalReplyCount":0,"publishedAt":"2020-01-31T09:52:39.000Z","replies":[]},{"id":"Ugz6YmIecDTGjiqg5d14AaABAg","comment":"මෙ වගෙ දුවෙක් ලබන්න එ තාත්ත කොච්චර පවු කරලා ඇද්ද...💧","author":"Don Shon","likeCount":1,"totalReplyCount":0,"publishedAt":"2020-01-31T09:33:04.000Z","replies":[]},{"id":"UgxkqbHuulk5kxXWGf14AaABAg","comment":"පුකේ ඇරියා නේද හොදට එල එල තව මාස පහ හයකින් තවත් එකෙක් ගාවට පලයන් වෙසියේ ඒක තොගේ පුරුද්දනේ එකෙක්ගේන් හුකා ගෙන මදිනේ වටේටම අල්ලපන් වෙසියේ හුත්ට පතුරු යනකන් වේසා හුත්ති ඒක කොල්ලෙක් අමරුවේ දැම්මා තොපි තමයි හොදම ගණිකාවෝ","author":"Sanjeewa makase","likeCount":0,"totalReplyCount":0,"publishedAt":"2020-01-31T09:20:20.000Z","replies":[]},{"id":"Ugyica7iO1Ud7EWh46V4AaABAg","comment":"Waradda budiya ganna ewath mewata dana ekai🙈🙈🙈","author":"nadu katu","likeCount":0,"totalReplyCount":0,"publishedAt":"2020-01-31T09:17:33.000Z","replies":[]},{"id":"Ugy98zUwDX-PWb7LpJt4AaABAg","comment":"අප්පට සිරි😂😂😂","author":"Nilanka Caldera","likeCount":0,"totalReplyCount":0,"publishedAt":"2020-01-31T09:15:09.000Z","replies":[]},{"id":"UgxcV6DdcafKrn3glnB4AaABAg","comment":"Ithin  kaatawath  moko . Aekige  thaththa  umbe  thaththa  neweyne.  Mae loke  hemotama  wadaa  oyata adarey  kiyana wachaneth ,maekey  wenasa  mokakda?","author":"Galle Untied","likeCount":0,"totalReplyCount":0,"publishedAt":"2020-01-31T09:15:04.000Z","replies":[]},{"id":"UgxIMqsvbIn0iScUkbt4AaABAg","comment":"Gahapu jathiya monaa unath hoda badu wage.wadila ridennama","author":"lakpriya madushanka","likeCount":0,"totalReplyCount":0,"publishedAt":"2020-01-31T09:09:28.000Z","replies":[]},{"id":"UgzLgjqKjxzSIten6g94AaABAg","comment":"Man nam mokuthma kiyanna na onna😂😂😂😂😂😂😂","author":"Hima Kumari","likeCount":0,"totalReplyCount":0,"publishedAt":"2020-01-31T09:05:50.000Z","replies":[]},{"id":"UgxvmHlfYBk8JB1jcSl4AaABAg","comment":"Topitat anunge huttak asse aegilla ගහල gada බලන්නේ netuwa පාඩුවේ inna be නේද","author":"Akila Nuwan","likeCount":0,"totalReplyCount":0,"publishedAt":"2020-01-31T09:05:18.000Z","replies":[]},{"id":"UgwJozNLeI6MwzGh0vV4AaABAg","comment":"අනේ මෙහෙම තන්හාවක්, අනේ මෙහෙම ආශාවක්....😂😂😂😂.......","author":"jwdm wijerathne","likeCount":1,"totalReplyCount":0,"publishedAt":"2020-01-31T08:59:40.000Z","replies":[]},{"id":"UgxDiYsuP4DuT_kT4pp4AaABAg","comment":"Me wolga nawai","author":"Jasintha Perera","likeCount":0,"totalReplyCount":0,"publishedAt":"2020-01-31T08:55:55.000Z","replies":[]},{"id":"UgyXtxP82U9OHTmfQFp4AaABAg","comment":"Oyawage wesiyanta thatha watinne na nodakin balu wesiyo thatha kiyanne deviyek wesiye","author":"Sudukumari Sudukumari","likeCount":0,"totalReplyCount":0,"publishedAt":"2020-01-31T08:42:10.000Z","replies":[]},{"id":"Ugzq1yYvPe2J7leUr-V4AaABAg","comment":"එයාගෙ තාත්තා අනික් දුවලගෙ තාත්තලට වඩා හොඳ නැතිව ඇති ඒ තාත්තා එයාලව බැලුවට වඩා හොඳට එයාගෙ ආදර වන්තයා හෝ සැමියා බලනවත් ඇති, නරැම තාත්තා කෙනෙකුට හොඳ කියන්න බැහැනෙ,ඒකයි එයාගෙ තාත්තාට වඩා වටින කෙනා කියල කියන්නෙ,වැරැද්දක් නැ ඔයාල තේරැම් ගන්න ඒක හැම තාත්තා කෙනෙක්ම දරැවන්ට හොඳින් යුතුකම් ඉටු කරන්නැ,බිරිඳ ඉද්දි තව ගෑනු පස්සෙ යන ,හම්බකරන දේ ඒ ගෑනුන්ට පුදන,ක්ලබ් යන, යාලුවන්ට බොන්න අරන් දෙන ඔය වගේ එයා අකමැති එක නොමනාකමක්  හරි එයාගෙ තාත්තත් කරනව ඇති ඒක දන්නෙ එයා, ඉතින් දැන් තේරෙනවනෙ හැම තාත්තලම එක විදිහට හිතන්නෙ නෑ කියල","author":"N.C FRANANDO","likeCount":1,"totalReplyCount":0,"publishedAt":"2020-01-31T08:34:58.000Z","replies":[]},{"id":"UgwfOuuRCTDDBdYtQap4AaABAg","comment":"මටනම් මේ ලෝකෙ මගෙ රත්තරන් තාත්තයි මගෙ රත්තරන් අම්මයි තරන් කිසිම එකෙක් වටින්නෙ na.ගැනුන්ට මිනිස්සුත් මිනිස්සුන්ට ගැනුත් ඕන තරන් හම්බ වෙනවා.නමුත්  අම්මා තාත්තා  කියන දෙන්න අපිට හම්බ වෙන්නේ ජීවිතේටම එකම එක පාරයි.ඒ උතුම් ආදරේ මන් හිතන්නෙ ne කාගෙන්වත් කාටවත්  ලැබෙයි කියල.","author":"Chandra Koumari","likeCount":0,"totalReplyCount":0,"publishedAt":"2020-01-31T08:31:09.000Z","replies":[]},{"id":"Ugxc2-TntM7STi0Utc14AaABAg","comment":"Mama asa niliyak ath me vidiyo aka baluwama kalakiruna thathata passe adare karapu akakma akkena kiuwanam kochara hodada","author":"رزانpatthare خالد","likeCount":0,"totalReplyCount":0,"publishedAt":"2020-01-31T08:30:03.000Z","replies":[]},{"id":"Ugy-LIJRTlaoWpdtzUN4AaABAg","comment":"Back side denne ranjatalu","author":"Ape vlogs Max","likeCount":0,"totalReplyCount":0,"publishedAt":"2020-01-31T08:06:14.000Z","replies":[]},{"id":"UgzVm3xhMtl7Dn8tkwt4AaABAg","comment":"Ubata adare karana akek nam ohoma video karala mehema prasidda maddayaka dan ne ..thathtekge adare thopi wage ayala yana unta watin ne teren neth ne ..uba en ne mathwela u en ne hoda sihiyen den harida ubata watin aka ubata karapu de .lejjai bola .aka pirimiyek amaruwe dala den harida ubata lejja weyan .","author":"hashi hashi","likeCount":0,"totalReplyCount":0,"publishedAt":"2020-01-31T08:03:31.000Z","replies":[]},{"id":"Ugy0ZUnfeuUhluXvBrd4AaABAg","comment":"පව් අර හර්ෂන අයියා .මේකි මහා කපටි ගැහැනියක් තූ නොදකින් මෙ වගෙ බැල්ලියෝ 😤😤😤😤","author":"Super Vlogs","likeCount":2,"totalReplyCount":0,"publishedAt":"2020-01-31T08:01:14.000Z","replies":[]},{"id":"UgxAUrfgTGHT2EHsbV94AaABAg","comment":"Meki wate yanawada bn kalin kolla nemaine me","author":"Lasiatha Sathsara","likeCount":0,"totalReplyCount":0,"publishedAt":"2020-01-31T07:50:26.000Z","replies":[]},{"id":"UgwGHN4qu2WlEy9Wwth4AaABAg","comment":"තම්න්ගෙ තාත්තා කවද්ද. තමන්ගෙ  දුගෙ නිරුවත ලෙකෙට පෙන්නන්නෙ. ඔයාට ඒතනම රිටන් එක මිනිහා දිලා නෙද. මිනිහම විඩියෝ කරලා  ලොකෙටම පෙන්නුවා නෙද. .....😂😂😂","author":"Pabelu Wharsha","likeCount":1,"totalReplyCount":0,"publishedAt":"2020-01-31T07:33:38.000Z","replies":[]},{"id":"UgwxxA9qSGAmWloYzDF4AaABAg","comment":"Me video eke inne wolka newei බොරුවක්","author":"Susantha Kasun","likeCount":0,"totalReplyCount":0,"publishedAt":"2020-01-31T07:27:09.000Z","replies":[]},{"id":"UgwV7JS7P-bqwdpbvXJ4AaABAg","comment":"Aiyo volga. Oya kata adare karath apita adala na. Eth video karagena chater wenna epa. Oyata api godak kamathi","author":"Red Eagle","likeCount":0,"totalReplyCount":0,"publishedAt":"2020-01-31T07:26:21.000Z","replies":[]},{"id":"UgzoZudJMW6d6yg0TL94AaABAg","comment":"Thathhata wada watinne  kawda ....pissu","author":"Santhi Vitharana","likeCount":0,"totalReplyCount":0,"publishedAt":"2020-01-31T07:25:44.000Z","replies":[]},{"id":"Ugylln-DG6aZM9_0T_J4AaABAg","comment":"ඔයාගේ පුද්ගලික දේවල් අපට අදාාාලම නැ එත් ඔයා නිළියක් හැටියට හිතන්න තිබුනා දෙමවිපියන්ට වඩා වටින දෙයක් මෙි ලෝකේ කිසිම තැනක නැ ඔයා ගැන ලැජ්ජයි","author":"Sudu Dhoni","likeCount":0,"totalReplyCount":0,"publishedAt":"2020-01-31T07:25:30.000Z","replies":[]},{"id":"UgzqYNlG7K6X-Di176Z4AaABAg","comment":"Me wage kunu video daala minissunge mole vikara karawanna epa thamange views wadi karaganna.wagakeemakin wadagath deyak daanna minissunta balanna.mokada podi daruwoth youtube balanawa.","author":"Achira Dharmarathne","likeCount":0,"totalReplyCount":0,"publishedAt":"2020-01-31T07:24:00.000Z","replies":[]},{"id":"UgyGRGOmrQPR4KYUK294AaABAg","comment":"Kohmat නළුවන්   නිළියන්  කියන්න \nAit අහන්න  dayak no tanikara\nහිරු  වගයි","author":"Wimalasooriya Himali","likeCount":0,"totalReplyCount":0,"publishedAt":"2020-01-31T07:22:46.000Z","replies":[]},{"id":"Ugw5EQ8EA6gmzwTSzX54AaABAg","comment":"Monawa unat adala ne mewa paw nodenuwatma meka samaja jalawala denmanam mokada palamu viwahen ain wela me miniha viswasa karala enne et den mewage ekak dekkama meyawa manasika wetei paw minissu viswasa karanna be","author":"RMSUBASHINI BALASURIYA","likeCount":0,"totalReplyCount":0,"publishedAt":"2020-01-31T07:22:02.000Z","replies":[]},{"id":"UgxaLy6ricRX7MIXUYx4AaABAg","comment":"ane apita moko puke amaruwateyanne untane  apitaya ubata ona nam thaththa akka budiya ganen kalalakanne weseyoo","author":"Mohammed Mohammed","likeCount":0,"totalReplyCount":0,"publishedAt":"2020-01-31T07:03:17.000Z","replies":[]},{"id":"Ugx-8VwfvMVSz1yvMJF4AaABAg","comment":"Aiye manike iwarai nada habi aka waraddaak tiyenwa matam watinne ammi ththi oyata ayawa hako  kamthak itin","author":"Shani Shani Shani","likeCount":0,"totalReplyCount":0,"publishedAt":"2020-01-31T07:01:49.000Z","replies":[]},{"id":"UgzjAtA-56hB1vtEEhV4AaABAg","comment":"Mum kalawa kala iwarae","author":"Lakmal Buddika","likeCount":0,"totalReplyCount":0,"publishedAt":"2020-01-31T06:55:15.000Z","replies":[]},{"id":"Ugw46N-3RYvA9kWTZ7p4AaABAg","comment":"Muntada minissu mahhara adara karanna nodakin","author":"Lakmal Buddika","likeCount":0,"totalReplyCount":0,"publishedAt":"2020-01-31T06:54:49.000Z","replies":[]},{"id":"UgyiyKkS5UH6igOBvA94AaABAg","comment":"කියන්න බැනෙ බන්,,,මේකිගෙ තාත්තාගෙ මොකක්හරි වරදක් තියනවද දන්නෙ නැනෙ,හරි තාත්තෙක්ගෙ හැදිච්ච දුවෙක්නම් මෙහෙම කියන්න විදියක් නැ,එක්කො දුවගෙ වැරැද්ද,නැත්තම් තාත්තගෙ වැරැද්ද ,මටනම් මේ ලෝකෙ දෙමාපියන්ට වඩා කෙනෙක් නැ,","author":"anushka anu","likeCount":0,"totalReplyCount":0,"publishedAt":"2020-01-31T06:53:36.000Z","replies":[]},{"id":"UgzSrXhNHUuPHMmn6y54AaABAg","comment":"Hitha ganna beha monawa kiyannada kiyala.","author":"Britney Britney","likeCount":0,"totalReplyCount":0,"publishedAt":"2020-01-31T06:48:17.000Z","replies":[]},{"id":"UgxrpM3QvzG5fI9ktpx4AaABAg","comment":"RESPECT FROM  DAUGHTER TO FATHER.👎🏿\nOYA YAKAA DAALA GIYOTH DEMAWPIYO WITHARAY  VOLGOO🤬","author":"Ajantha Siriwardena","likeCount":0,"totalReplyCount":0,"publishedAt":"2020-01-31T06:46:25.000Z","replies":[]},{"id":"UgzUWOV2hTmSmSI7CUB4AaABAg","comment":"Nalu niliyo kiyala kiyanne dan nam jarama jathiyak","author":"Inoka Priyadarshani","likeCount":0,"totalReplyCount":0,"publishedAt":"2020-01-30T18:23:27.000Z","replies":[]},{"id":"UgzjcUt5QKy4AfcPpLZ4AaABAg","comment":"Ammma thaththa nisa thamai patta balliye uba me loketa aweth.   Thoge wanacharakam walata e minussu pali na. Balli","author":"Samith Madushan","likeCount":0,"totalReplyCount":0,"publishedAt":"2020-01-30T15:30:34.000Z","replies":[]},{"id":"Ugxa8CaIZCYKA9AZ9054AaABAg","comment":"Pala wasi yanna maga Sri Lankawa kanna natuwa","author":"Hisan Wejasuriya","likeCount":0,"totalReplyCount":0,"publishedAt":"2020-01-30T14:06:08.000Z","replies":[]},{"id":"UgypARSq96LweNgl9kZ4AaABAg","comment":"තොටහොදනමිි අපිට මොකෝ","author":"weerasuriya lasantha","likeCount":0,"totalReplyCount":0,"publishedAt":"2020-01-28T14:58:58.000Z","replies":[]},{"id":"UgxAf1rbY80jW8mfzDF4AaABAg","comment":"තාත්තට වඩා වටිනවා කීවේ... මස් කඩේට ව්කුනන්නද???......😨","author":"Dhammika Prasanna","likeCount":1,"totalReplyCount":0,"publishedAt":"2020-01-28T14:13:55.000Z","replies":[]},{"id":"Ugw-NPLACzO67IE0tyV4AaABAg","comment":"අපිටනන්තාත්තාටවැඩිය\nමෙලොකෙක\nඋරුවත්නැ","author":"Siriyani Siriyani","likeCount":1,"totalReplyCount":0,"publishedAt":"2020-01-28T09:41:45.000Z","replies":[]},{"id":"UgxK1IZuGfFXO1eH9Wt4AaABAg","comment":"බඩුවක් උනාම එහෙම තමා","author":"Hjs Hhs","likeCount":0,"totalReplyCount":0,"publishedAt":"2020-01-28T07:42:04.000Z","replies":[]},{"id":"UgzmPyaSaotNN3BPTfd4AaABAg","comment":"ඔච්චර ආදරෙයි නම් ඔහොම vedio දාන්නෙ නැනෙ ඒ මිනිහ","author":"Nadee danu","likeCount":8,"totalReplyCount":0,"publishedAt":"2020-01-28T07:30:35.000Z","replies":[]},{"id":"UgxFLPnMUQUBwnmqXyB4AaABAg","comment":"Tattage teyenne daruwekuta teyena adare.Yalu wena pereme laga teyenne kamuka adare .aka terunganna bare weseyak","author":"shirome sandamale","likeCount":0,"totalReplyCount":0,"publishedAt":"2020-01-28T05:07:08.000Z","replies":[]},{"id":"UgxkDYYz-Gzv7GgEKeZ4AaABAg","comment":"පිය සෙනහස කගෙන්වත් ලබෙන් නැත කියලා හිතෙන  නෙද් පිස්සු විකාර නොකියා දැන්වත් ඉන්නවා","author":"sss Pradeep","likeCount":0,"totalReplyCount":0,"publishedAt":"2020-01-28T04:27:17.000Z","replies":[]},{"id":"UgxNmKHkLQyrYGY2i-V4AaABAg","comment":"හර්ෂණ aiyata mkd wenne","author":"kaveesha wanni arachchi","likeCount":0,"totalReplyCount":1,"publishedAt":"2020-01-28T04:09:59.000Z","replies":[{"parentId":"UgxNmKHkLQyrYGY2i-V4AaABAg","authorDisplayName":"Krishanthi Rasangika","replyComment":"akane.paw neda....","publishedAt":"2020-01-28T18:24:43.000Z","likeCount":0}]},{"id":"Ugw5VlJR04tCs4lRyyp4AaABAg","comment":"ටෙලිනාට්‍යක්ද කොහෙද 😃😃😃","author":"Shayama K K","likeCount":0,"totalReplyCount":0,"publishedAt":"2020-01-28T03:59:16.000Z","replies":[]},{"id":"UgygxKqhuoJR6FU2DO54AaABAg","comment":"නොදකින් නෝදෝමකින් ගොම්කම ලෝකටම ප්‍රදර්ශනය කරන මෝඩි.අම්මා තාත්තා තරම් වටින කෙනෙක් ඉන්නවද මේ ලෝකේ.මෝඩම මෝඩියක්.ඕව කියපිය මිනිහට ඇහෙන්න විතරක්.","author":"Udeni Alagiyawanna","likeCount":0,"totalReplyCount":0,"publishedAt":"2020-01-28T03:51:13.000Z","replies":[]},{"id":"UgyM83S_vKmBg6yzg5Z4AaABAg","comment":"Awalan wesiye ! Tho moka ekka hemununath apata mokada ! Thopi mewa lejja netiwa danawane !","author":"layan hart","likeCount":0,"totalReplyCount":0,"publishedAt":"2020-01-28T02:50:42.000Z","replies":[]},{"id":"UgzGszA6GI1nY-seduh4AaABAg","comment":"Ane bola thamange thathatharanm kuruth watinna","author":"Wasanthi Kumari","likeCount":0,"totalReplyCount":0,"publishedAt":"2020-01-28T02:22:32.000Z","replies":[]},{"id":"Ugw7Q2xlGp_Kr6w2Am14AaABAg","comment":"Gon vesi","author":"sri Lankan youtube","likeCount":0,"totalReplyCount":0,"publishedAt":"2020-01-28T02:05:46.000Z","replies":[]},{"id":"UgxXNkt_UDQjbG_dXbB4AaABAg","comment":"Are u kidding me බෙත්මගේ අයියා","author":"Pasindu Akash","likeCount":0,"totalReplyCount":0,"publishedAt":"2020-01-28T01:53:07.000Z","replies":[]},{"id":"UgzecUFkThTzBudx0CZ4AaABAg","comment":"nodokin patta wesiii","author":"Ajith Kumara","likeCount":0,"totalReplyCount":0,"publishedAt":"2020-01-28T01:40:28.000Z","replies":[]},{"id":"UgzGPwITeNVj4XcKpHV4AaABAg","comment":"🤐","author":"Harsha Sandaruwan","likeCount":0,"totalReplyCount":0,"publishedAt":"2020-01-28T01:17:31.000Z","replies":[]},{"id":"UgyjnNLNgm8eLMTTYFV4AaABAg","comment":"Link eka naddooo😁😁😊","author":"SL E TECK","likeCount":0,"totalReplyCount":0,"publishedAt":"2020-01-28T01:07:53.000Z","replies":[]},{"id":"UgzytrOTyPZz2bX78Sh4AaABAg","comment":"මේ හොල්මන එලෝ විකාරෙන් දොඩවනවද කොහෙද .","author":"Saumya Perera","likeCount":0,"totalReplyCount":0,"publishedAt":"2020-01-27T22:45:38.000Z","replies":[]},{"id":"UgxbyG6SPPB6kBvzfsh4AaABAg","comment":"Meki unne. Pathtini amma wage. Thada baduwakne","author":"Marie shanima Perera","likeCount":0,"totalReplyCount":0,"publishedAt":"2020-01-27T22:30:20.000Z","replies":[]},{"id":"UgyDNbep9gbLQ7CiWL14AaABAg","comment":"තූ .... නොදකින් ......","author":"Anuhsa Sandhya","likeCount":0,"totalReplyCount":0,"publishedAt":"2020-01-27T22:27:57.000Z","replies":[]},{"id":"UgxdvilDf_kmJw8vEop4AaABAg","comment":"වෙන කිසිම කෙනෙක් ඔහම කියලම නැද්ද  😆😆😆😆","author":"Sriyani Jayalath","likeCount":1,"totalReplyCount":0,"publishedAt":"2020-01-27T22:19:50.000Z","replies":[]},{"id":"UgwTPWHekcEGRTEFxSh4AaABAg","comment":"සමහර විට තාත්තාගේ ආදරයක් හම්බෙලා නැතුව ඇති.මේ සමාජේ ඕන තරම් අපිට දකින්න ලැබෙනවනෙ.මගෙ තාත්තගේ ආදරෙ මට ලැබුනා.ඉතින් තාත්තට අම්මට පස්සෙ අනිත් හැම දේම.එහම කියන්න වටින්න හේතු ඇතී.එයාලට අව්ලක් නැත්තම් ඇයි අපි අව්ල් වෙන්නේ.","author":"Sriyani Jayalath","likeCount":2,"totalReplyCount":1,"publishedAt":"2020-01-27T22:12:24.000Z","replies":[{"parentId":"UgwTPWHekcEGRTEFxSh4AaABAg","authorDisplayName":"Shalani Ish","replyComment":"Oya godak buddimat kenek....oya hitanawa Hari....","publishedAt":"2020-01-28T08:28:33.000Z","likeCount":0}]},{"id":"UgzI46tX8gb8uq5e-o94AaABAg","comment":"Mekita pissu","author":"Spain Phone","likeCount":0,"totalReplyCount":0,"publishedAt":"2020-01-27T21:37:51.000Z","replies":[]},{"id":"UgzOKdZftytLv3huNX14AaABAg","comment":"Nidakin kala kanni wesiyo hena gahapiya thopita","author":"දෙදුනු දෙදුනු","likeCount":0,"totalReplyCount":0,"publishedAt":"2020-01-27T21:12:38.000Z","replies":[]},{"id":"UgyVJjsNo35vhkQJ6V54AaABAg","comment":"Mona gon baduwakda ban ma","author":"Amal Dinusha","likeCount":0,"totalReplyCount":0,"publishedAt":"2020-01-27T21:07:13.000Z","replies":[]},{"id":"Ugy9SeHdK5ZJZxYuKoB4AaABAg","comment":"Nodakin balu wesiyek","author":"Rasika Sampath","likeCount":0,"totalReplyCount":0,"publishedAt":"2020-01-27T20:59:08.000Z","replies":[]},{"id":"UgzcJUvTHjDQ_K_I5pF4AaABAg","comment":"oya miniha gani podi lamayai dala awith enna lassana","author":"dilshani d","likeCount":0,"totalReplyCount":0,"publishedAt":"2020-01-27T20:52:23.000Z","replies":[]},{"id":"Ugyv_MDVoN6SHNAbHYl4AaABAg","comment":"තුක් නොදකින්","author":"HARALD WYLIE","likeCount":0,"totalReplyCount":0,"publishedAt":"2020-01-27T20:26:16.000Z","replies":[]},{"id":"Ugy8Otzw55Zi1z9tnfJ4AaABAg","comment":"නොදකින් පට්ට වේසි ....තාත්තටත් වඩා තොට මූව වටිනවනම් තෝ කාපිය මගෙ ගූ.","author":"Jayntha Udaya","likeCount":0,"totalReplyCount":0,"publishedAt":"2020-01-27T20:22:37.000Z","replies":[]},{"id":"Ugx5DG9A0Aq29cSroa14AaABAg","comment":"මෙතන වැරදි මිනිස්සු විශ්වාස කරලා හැමදේම පූජා කරන ගෑනු. වීඩියෝ කරන්නේ මිනිහනේ. මීඩියා වලට දෙන්නෙත් මිනිහා. විශ්වාස කරන එකයි වැරැද්ද","author":"Kanchana Dilrukshi","likeCount":11,"totalReplyCount":3,"publishedAt":"2020-01-27T20:21:35.000Z","replies":[{"parentId":"Ugx5DG9A0Aq29cSroa14AaABAg","authorDisplayName":"Chandi layal","replyComment":"සහතික ඇත්ත අනේ","publishedAt":"2020-01-31T07:22:52.000Z","likeCount":0},{"parentId":"Ugx5DG9A0Aq29cSroa14AaABAg","authorDisplayName":"Road life","replyComment":"Hariyatama හරි.. 🤔 Me hema දේටම මුල ආසාව විතරයි.. Adarey ආසාවy ඉස්සරha gaanu අන්ධ වෙනව.. අන්තිමට ඉන්නෙත් අම්මයි තාත්තයි විතරයි..","publishedAt":"2020-01-27T23:04:23.000Z","likeCount":3},{"parentId":"Ugx5DG9A0Aq29cSroa14AaABAg","authorDisplayName":"Sriyani Jayalath","replyComment":"Eka nam aththa.","publishedAt":"2020-01-27T22:06:11.000Z","likeCount":1}]},{"id":"Ugx-YIPq3fiX_SnKVhR4AaABAg","comment":"Nodakin balli","author":"Kumari Kumari","likeCount":0,"totalReplyCount":0,"publishedAt":"2020-01-27T19:54:32.000Z","replies":[]},{"id":"UgxYG--5wehxNGsoLPN4AaABAg","comment":"අපරාදෙ බන් අර වෙඩින් එකට වියදම් කරපු සල්ලි...නැති බැරි මිනිහෙක්ට දුන්නානම් ඊට වඩ හොදයි ..ඕකයි කලා ලොවේ අලුත් විස්තර අහ් 💣","author":"Dilani Harshamala","likeCount":4,"totalReplyCount":0,"publishedAt":"2020-01-27T19:46:55.000Z","replies":[]},{"id":"Ugzyiykk2DzGk9LAcpZ4AaABAg","comment":"Munta pissu balu roga hadelada kohada","author":"Yamuna Sudarshini","likeCount":0,"totalReplyCount":0,"publishedAt":"2020-01-27T19:32:28.000Z","replies":[]},{"id":"Ugxyuve-K-sj3-6R9Xt4AaABAg","comment":"කියන්න වදන් නෑ ...😌😌🙄🙄","author":"tharaka hirushan","likeCount":0,"totalReplyCount":0,"publishedAt":"2020-01-27T19:26:02.000Z","replies":[]},{"id":"UgyVdVqy7S8sYNrdHr94AaABAg","comment":"ඔන්නෙ නැති මගුලක් නැ අප්පා අපිට මොකද අනෙ","author":"Nesto Nesto","likeCount":15,"totalReplyCount":0,"publishedAt":"2020-01-27T19:21:58.000Z","replies":[]},{"id":"Ugzc0VnddKaFszSwDu54AaABAg","comment":"Me volga neme","author":"dufsts csfsdaa","likeCount":0,"totalReplyCount":1,"publishedAt":"2020-01-27T19:12:48.000Z","replies":[{"parentId":"Ugzc0VnddKaFszSwDu54AaABAg","authorDisplayName":"Shayama K K","replyComment":"වොල්ගා නෙවෙයි නම් කටහඬ ?","publishedAt":"2020-01-28T03:54:54.000Z","likeCount":0}]},{"id":"Ugzb2uCCauEwhULF_qt4AaABAg","comment":"අනේ මේකි.දෙමාපියන්ට  වඩා කවුද  මේ ලෝකේ වටින්නේ.ගොන් ගෑනූ","author":"Subasinghe Subasinghe","likeCount":1,"totalReplyCount":0,"publishedAt":"2020-01-27T19:03:28.000Z","replies":[]},{"id":"Ugwfn5FJjmzFp7ynG2B4AaABAg","comment":"maki kokan gahalada kohada","author":"كويت كويت","likeCount":0,"totalReplyCount":0,"publishedAt":"2020-01-27T18:55:36.000Z","replies":[]},{"id":"UgySeGv5P_7vIC8QRx14AaABAg","comment":"මේකි මොනවා හරි මත්ද්‍රව්‍යයක් පාවිච්චි කරලද කොහෙදො","author":"Thusi Uagh","likeCount":3,"totalReplyCount":0,"publishedAt":"2020-01-27T18:52:33.000Z","replies":[]},{"id":"UgwiPhdUy5Mmdw3aljF4AaABAg","comment":"Matanam lankawen wedi purama asama niliyekta inne pooja umasankar  and thisuri yuwanika  witharai anith un hodai kala renna","author":"Chinthaka Kumara","likeCount":2,"totalReplyCount":2,"publishedAt":"2020-01-27T18:39:33.000Z","replies":[{"parentId":"UgwiPhdUy5Mmdw3aljF4AaABAg","authorDisplayName":"Hg Chin","replyComment":"Eka atta","publishedAt":"2020-01-31T09:41:37.000Z","likeCount":0},{"parentId":"UgwiPhdUy5Mmdw3aljF4AaABAg","authorDisplayName":"Sriyani Jayalath","replyComment":"ඔව් අනේ.ඒ දෙන්නා ඒ දෙන්නා සල්ලි වලට රග පෑවට ඇත්තටම සරලව ඉන්න දෙන්නෙක්.","publishedAt":"2020-01-27T22:15:51.000Z","likeCount":0}]},{"id":"UgzSH9b3BAjDoLig0UR4AaABAg","comment":"Yako thaman poliy kaleidala hadawapu wadapu demapiyo thogi wasakamata dewani kara ganna epa. Wasaballiy yako thoge wasakamata demapiyo. Pawanna epa","author":"Manjula Manjula","likeCount":0,"totalReplyCount":0,"publishedAt":"2020-01-27T18:37:42.000Z","replies":[]},{"id":"Ugx3arJ9NNP0IpkY6pF4AaABAg","comment":"මේ ගෑනි කුඩු ගහලද කොහෙද. හර්ෂණ උඹේ පින නිසා බේරුනෙ","author":"Upul Nishan","likeCount":0,"totalReplyCount":0,"publishedAt":"2020-01-27T18:37:12.000Z","replies":[]},{"id":"Ugz1iPvZ_6RedJ0FHxZ4AaABAg","comment":"Me banala comments dala thiyena un palamu Adara wanthiya ho palamu Adara wanthayawa wenna athi kasada bande wena eakek Athinwath allala nathuwa athiea lankawea un easso wagea","author":"حاول ا","likeCount":0,"totalReplyCount":0,"publishedAt":"2020-01-27T18:34:33.000Z","replies":[]},{"id":"UgzxpwecS0jD75Gm3u14AaABAg","comment":"ඉරිසියාකාරයො කියයි ඉතින් කතා.. දුන්නනම් බලන්න තිබුන අපෙ අප්පලගෙ වැඩ...","author":"Sampath Kumara","likeCount":1,"totalReplyCount":0,"publishedAt":"2020-01-27T18:14:49.000Z","replies":[]},{"id":"UgxO2UcOTC_Ndt26-OZ4AaABAg","comment":"Nodakin miki තාත්තා  කොයිතරම්  watina wasthuwakda mikita madana wise","author":"Kumari Perera","likeCount":0,"totalReplyCount":0,"publishedAt":"2020-01-27T18:07:18.000Z","replies":[]},{"id":"UgyRZGvx1vKKtAX73Ph4AaABAg","comment":"මුන්ට  පිස්සු","author":"Kumari Suduhakuruge","likeCount":0,"totalReplyCount":0,"publishedAt":"2020-01-27T17:15:19.000Z","replies":[]},{"id":"UgzhI408xRZqgtVO-x14AaABAg","comment":"දැන් සනිපයි නේ 😂😂😂😂😂😂😂😂","author":"Chamila Wasanthi","likeCount":0,"totalReplyCount":0,"publishedAt":"2020-01-27T17:06:31.000Z","replies":[]},{"id":"UgyEs8qt1aiG7dsDK-d4AaABAg","comment":"Ranjata kiyala puke arawagaththanam oita hondaine sudu.","author":"udaya chamara","likeCount":0,"totalReplyCount":0,"publishedAt":"2020-01-27T17:05:18.000Z","replies":[]},{"id":"UgwdyfdlF3hTBvHeAlF4AaABAg","comment":"ඔය කෙරුවෙ ....වැරැද්ද 🤗🤗🤗🤗🤗","author":"i fernando","likeCount":1,"totalReplyCount":0,"publishedAt":"2020-01-27T16:47:55.000Z","replies":[]},{"id":"Ugy6pggggELpvgZu-ct4AaABAg","comment":"😂😂😂😂😂😂😉😉😉😉😉😉😉","author":"n n","likeCount":0,"totalReplyCount":0,"publishedAt":"2020-01-27T16:31:17.000Z","replies":[]},{"id":"UgwTE9_7BbRTIU2fukl4AaABAg","comment":"Ane pako meka waradak me kena  badueak kiyla  kiyanna puluwanda .meka thama yako adare kiyanne Ade dagena hukana eka newei g.l akke oyatai aiyatai b.s","author":"Kasun Anuraja","likeCount":1,"totalReplyCount":0,"publishedAt":"2020-01-27T16:27:33.000Z","replies":[]},{"id":"UgzlXZgY52PX0MVjwz54AaABAg","comment":"My god    please  thinking  fist  about  mother  father   only  can belive  mother & father  in. World  mother father  is our god don't  forget  thete    Eny men or Eny ledy  newer  can belive   I hope  some  have  but  we don't know  who  is the good  wery wery  difficult  find  some  one  good  please  keep  Maind  mother father  is god  don't  forget","author":"padmini ekanayaka","likeCount":0,"totalReplyCount":0,"publishedAt":"2020-01-27T16:14:13.000Z","replies":[]},{"id":"UgwlAvmLBh6h4zSpFWd4AaABAg","comment":"Pana wage hitiyata wen vila giye data pem loke mathaka tika kalayai yalu. Mother father adare ehema na.","author":"Sriyana Maine","likeCount":0,"totalReplyCount":0,"publishedAt":"2020-01-27T16:06:14.000Z","replies":[]},{"id":"UgwHyvhWJO4jXY_5Uo14AaABAg","comment":"අය්යෝ හැමීනෙනවා මුන් ග‍ගු෴..වේනවා","author":"Rehan danu","likeCount":0,"totalReplyCount":0,"publishedAt":"2020-01-27T15:57:15.000Z","replies":[]},{"id":"UgwAVbywKvXGSDAyZ7l4AaABAg","comment":"තාත්තා ගෙ ආදරෙ සැමියගෙ ආදරෙ කියන්නෙ දෙකක් කියන එක තෙරුම් නොගත්ත ගොං වැස්සියෙක් ගෙ කතාවක්,,,","author":"Manori Priyadarshani","likeCount":30,"totalReplyCount":1,"publishedAt":"2020-01-27T15:54:48.000Z","replies":[{"parentId":"UgwAVbywKvXGSDAyZ7l4AaABAg","authorDisplayName":"kusal kavinda","replyComment":"Manori Priyadarshani ubata itin eka adala nene","publishedAt":"2020-01-31T10:50:35.000Z","likeCount":1}]},{"id":"Ugy-r6LPUvRQWwCohbp4AaABAg","comment":"Mage thathatha nethi wela eth adatath man adare mage thaththata me loke man adare kale mage thaththata","author":"Nalany hawile","likeCount":3,"totalReplyCount":0,"publishedAt":"2020-01-27T15:44:40.000Z","replies":[]},{"id":"Ugx__UaKumAjHlZlwTl4AaABAg","comment":"Volga  way  tokin  you  father  not  good  jesus  given  punish  you  okay","author":"Milani Mila","likeCount":0,"totalReplyCount":0,"publishedAt":"2020-01-27T15:42:07.000Z","replies":[]},{"id":"Ugz6OaO3xzOSkz2zfkp4AaABAg","comment":"ආදරය කාටත් වරදිනවා කවුරුත් අසරණ වෙනවා ...😎😎","author":"wonderful videoworld","likeCount":20,"totalReplyCount":0,"publishedAt":"2020-01-27T15:28:56.000Z","replies":[]},{"id":"UgwyWkmD4G-zoS5thnV4AaABAg","comment":"Man essara wolgata kemathi at dennam ne ahema hituna kattiya kament akak dan yandoo","author":"K Maduwanthi","likeCount":4,"totalReplyCount":1,"publishedAt":"2020-01-27T15:27:50.000Z","replies":[{"parentId":"UgwyWkmD4G-zoS5thnV4AaABAg","authorDisplayName":"Nilantha Chandimal","replyComment":"Ow neda","publishedAt":"2020-01-31T07:30:38.000Z","likeCount":0}]},{"id":"UgweHizjU5VgW4REOep4AaABAg","comment":"මේ කාන්තාවගෙ තාත්ත මෙයාට ආදරේ නැතුව ඇති...","author":"Sandy Fernando","likeCount":3,"totalReplyCount":0,"publishedAt":"2020-01-27T15:19:37.000Z","replies":[]},{"id":"UgwpUcoINmhWwuJW7_R4AaABAg","comment":"අනේ බැල්ලි අපිනම් මේ ලෝකේ වටින ඒකම දේ තමයි අම්මා සහ තාත්තයි","author":"Laga Latta","likeCount":5,"totalReplyCount":2,"publishedAt":"2020-01-27T15:08:22.000Z","replies":[{"parentId":"UgwpUcoINmhWwuJW7_R4AaABAg","authorDisplayName":"ජයන්ති ජයන්ති","replyComment":"Aniwarayenma ekita pissuda koha demaupiyo taram watina wasthuwak tawath tiyanawada","publishedAt":"2020-01-31T06:44:54.000Z","likeCount":0},{"parentId":"UgwpUcoINmhWwuJW7_R4AaABAg","authorDisplayName":"Shalani Ish","replyComment":"Eyya hariyata katakarannawat ammi tatti uganwala Neha oyata","publishedAt":"2020-01-28T08:26:58.000Z","likeCount":0}]},{"id":"UgyMzDG6QXfA8qDVPV54AaABAg","comment":"Nodakin vitharak","author":"Mahapitiya sadu!! sadu!!sadu!!! Soma","likeCount":0,"totalReplyCount":0,"publishedAt":"2020-01-27T15:06:15.000Z","replies":[]},{"id":"UgwWjeu-IhxQqj5HL3N4AaABAg","comment":"පව් අර හර්ශන අයියා... මේකිට රැවටුනානේ😠😠","author":"Thusindu. Muses","likeCount":19,"totalReplyCount":0,"publishedAt":"2020-01-27T14:59:09.000Z","replies":[]},{"id":"UgyRfLu3pDGHCli83et4AaABAg","comment":"මුන් tv එක ඉස්සරහ බොරුවට පොෂ් වෙන්න හැදුවට, සාමාන්‍ය ජීවිතේදී පට්ට ගෝඩේ විදියටනේ කතා කරන්නෙ, \n\"මේ ඉන්නේඒඒ\nමගේ ජීවිතේඒඒඒ\nමගේ තාත්තාටත් වැඩියයයඅඅ\nගොඩාක් වටිනඅඅඅ\"\nනම වොල්ගා උනාට accent එකෙන්නම් \"කරුණාවතී\" වගේ 😂😂😂😂😂😂😂😂","author":"T N","likeCount":23,"totalReplyCount":3,"publishedAt":"2020-01-27T14:55:55.000Z","replies":[{"parentId":"UgyRfLu3pDGHCli83et4AaABAg","authorDisplayName":"lakpriya madushanka","replyComment":"Oi eka😂😂","publishedAt":"2020-01-31T09:07:51.000Z","likeCount":0},{"parentId":"UgyRfLu3pDGHCli83et4AaABAg","authorDisplayName":"Hjs Hhs","replyComment":"🤣🤣🤣","publishedAt":"2020-01-29T07:34:23.000Z","likeCount":0},{"parentId":"UgyRfLu3pDGHCli83et4AaABAg","authorDisplayName":"Chathuri Dinu","replyComment":"Apoi mata ba...😂😂😂","publishedAt":"2020-01-28T00:31:40.000Z","likeCount":0}]},{"id":"UgxQJ-7o-qNdXEQCjMN4AaABAg","comment":"mokunda bn me .mekita thaththata wada watina,rata rata buduyaganna pirimi watinawada bn.mona ganiyakda","author":"Pissu Cinema","likeCount":0,"totalReplyCount":0,"publishedAt":"2020-01-27T14:54:20.000Z","replies":[]},{"id":"Ugx130EXUPd6m7zph3Z4AaABAg","comment":"huththiii wesi","author":"Sanaka Kumara","likeCount":0,"totalReplyCount":0,"publishedAt":"2020-01-27T14:43:51.000Z","replies":[]},{"id":"Ugw0Bsn83X2f5Vuupm14AaABAg","comment":"Nidiyana awath vediyo danna molla kuruwal walada kasada minihawa lebuna thaththata kalinda ranjanalaga ganata wetila","author":"Lath A","likeCount":0,"totalReplyCount":0,"publishedAt":"2020-01-27T14:37:10.000Z","replies":[]},{"id":"UgyhiJc-PIH6tddLA7h4AaABAg","comment":"මම නම් මේකේ දකින වැරැද්ද මේ ලෝකෙ තාත්තටත් වැඩිය වටින කෙනා කියපු වචනය විතරයි. මොකද දුවෙකුට තාත්තෙක් තරම් මේ ලෝකෙ කිසිම පිරිමියෙකුට ආදරය කරන්න බෑ ඒ ආදරය අසමසමයි ඒක නිසා. අනිත් දේවල් නම් එයාගේ පෞද්ගලික ජීවිතයනේ. එයාලට හොදනම් අනිත් අයට මොකෝ...😏😏😏","author":"Dinusha Lakmali","likeCount":59,"totalReplyCount":6,"publishedAt":"2020-01-27T14:35:06.000Z","replies":[{"parentId":"UgyhiJc-PIH6tddLA7h4AaABAg","authorDisplayName":"Isac Hewa","replyComment":"Aththamai  thaththa dakkama  kochchara  duka  hitheida?","publishedAt":"2020-01-31T07:57:25.000Z","likeCount":1},{"parentId":"UgyhiJc-PIH6tddLA7h4AaABAg","authorDisplayName":"pathma kumari kapugedara","replyComment":"Thamange thaththata neda ehema kiyanne","publishedAt":"2020-01-28T15:38:47.000Z","likeCount":0},{"parentId":"UgyhiJc-PIH6tddLA7h4AaABAg","authorDisplayName":"pathma kumari kapugedara","replyComment":"Oyata newei","publishedAt":"2020-01-28T15:37:32.000Z","likeCount":0},{"parentId":"UgyhiJc-PIH6tddLA7h4AaABAg","authorDisplayName":"Dinusha Lakmali","replyComment":"@pathma kumari kapugedara කාටද ඔයා එහෙම කියන්නේ?","publishedAt":"2020-01-27T22:47:33.000Z","likeCount":0},{"parentId":"UgyhiJc-PIH6tddLA7h4AaABAg","authorDisplayName":"pathma kumari kapugedara","replyComment":"පිස්සු ගෑනීයෙක්","publishedAt":"2020-01-27T17:58:37.000Z","likeCount":0},{"parentId":"UgyhiJc-PIH6tddLA7h4AaABAg","authorDisplayName":"Theroj Diashan","replyComment":"Wadak na kiyala chuty kale indan atha patha gala hadapu thathata wada mee kohewath yanewa minihek loku keran lajjai ah.❤","publishedAt":"2020-01-27T16:31:00.000Z","likeCount":0}]},{"id":"UgzkwXO5KDmv2ViUN0N4AaABAg","comment":"තාත්තාටත් වැඩිය වටිනවලු 😯😯😯😯😯 අපිටනම් මේ ලෝකේ වැඩියෙන්ම වටින්නේ අම්මයි තාත්තයි","author":"අනු හංසි","likeCount":85,"totalReplyCount":12,"publishedAt":"2020-01-27T14:32:49.000Z","replies":[{"parentId":"UgzkwXO5KDmv2ViUN0N4AaABAg","authorDisplayName":"Road life","replyComment":"@Muthee Perera 🤔👍ඇත්ත ඔයා හරි.. එහෙම උනාම ලමයින්ට එපා වෙනවා.. අම්මලා ගොඩක් අසරණ වෙනවා.. Eth පිරිමි 100ta 100k විශ්වාස කරන්න බැහැ..මූලික අවශ්‍යතාවය ඉටු කරගත්තා ම ඉබේම ආදරේ අඩුවෙනවා.. එහෙම කෙනෙක් hamuඋනොත් kellage jeewithe ඉතුරු ටිකත් ඉවරයි.. Honda කෙනෙක් hamba උනොත් ජීවිතේ 🌹","publishedAt":"2020-01-31T14:56:59.000Z","likeCount":0},{"parentId":"UgzkwXO5KDmv2ViUN0N4AaABAg","authorDisplayName":"Muthee Perera","replyComment":"Ehema watina demawpiyoth innawa...punchi kaalema dala yana thathala?? Matanam amma vitharai watinne ..","publishedAt":"2020-01-31T12:36:57.000Z","likeCount":1},{"parentId":"UgzkwXO5KDmv2ViUN0N4AaABAg","authorDisplayName":"Hjs Hhs","replyComment":"අනිවා","publishedAt":"2020-01-31T10:58:06.000Z","likeCount":1},{"parentId":"UgzkwXO5KDmv2ViUN0N4AaABAg","authorDisplayName":"Samith Madushan","replyComment":"Hm hmmmm","publishedAt":"2020-01-31T09:43:47.000Z","likeCount":0},{"parentId":"UgzkwXO5KDmv2ViUN0N4AaABAg","authorDisplayName":"MADHURIKA HEWAWASAM Dilrukshi","replyComment":"අනේ ද කියන්නේ පලමුතැන දෙමව්පියෝ දෙන්න ඊටපස්සේ තමයි වෙන අය","publishedAt":"2020-01-31T09:25:20.000Z","likeCount":1},{"parentId":"UgzkwXO5KDmv2ViUN0N4AaABAg","authorDisplayName":"Nalani Samarathna","replyComment":"Akanm attha okun raga pana aunne okuth ragapamak kiyala hitagamu amma tatthata wada deyak apitanm na kalakanni jatiyak ohma hitana daruwo inna nisha tamai wadi heti niwasha wadei wanne lankawa","publishedAt":"2020-01-31T08:24:11.000Z","likeCount":1},{"parentId":"UgzkwXO5KDmv2ViUN0N4AaABAg","authorDisplayName":"Samith Madushan","replyComment":"@chuti chuti hareee☺☺☺","publishedAt":"2020-01-31T08:06:02.000Z","likeCount":0},{"parentId":"UgzkwXO5KDmv2ViUN0N4AaABAg","authorDisplayName":"chuti chuti","replyComment":"Ow  ething  ke patthata awa ada","publishedAt":"2020-01-31T08:00:43.000Z","likeCount":1},{"parentId":"UgzkwXO5KDmv2ViUN0N4AaABAg","authorDisplayName":"Samith Madushan","replyComment":"@chuti chuti aaaaa  meyath awith☺","publishedAt":"2020-01-31T07:45:37.000Z","likeCount":1},{"parentId":"UgzkwXO5KDmv2ViUN0N4AaABAg","authorDisplayName":"chuti chuti","replyComment":"Ani waryanma","publishedAt":"2020-01-31T07:19:42.000Z","likeCount":1},{"parentId":"UgzkwXO5KDmv2ViUN0N4AaABAg","authorDisplayName":"Prbath Shyamika","replyComment":"Aniwaryanma nangi atta oyaga katawa","publishedAt":"2020-01-31T07:03:53.000Z","likeCount":0},{"parentId":"UgzkwXO5KDmv2ViUN0N4AaABAg","authorDisplayName":"Samith Madushan","replyComment":"Hariyatama hari","publishedAt":"2020-01-30T15:28:33.000Z","likeCount":0}]},{"id":"Ugyn1rBN2cQjMpt8jtp4AaABAg","comment":"පත්තිනි අම්මලා ටිකගේ comments balapallako එකි මොකා එක්ක හිටියත් අපට මොකො","author":"Samsung J4","likeCount":60,"totalReplyCount":53,"publishedAt":"2020-01-27T14:32:39.000Z","replies":[{"parentId":"Ugyn1rBN2cQjMpt8jtp4AaABAg","authorDisplayName":"Shasha Shasha","replyComment":"ඇත්ත","publishedAt":"2020-02-18T05:36:01.000Z","likeCount":0},{"parentId":"Ugyn1rBN2cQjMpt8jtp4AaABAg","authorDisplayName":"Ape Sri lankawa","replyComment":"Mun vage un anivaryenma apaye","publishedAt":"2020-02-02T14:14:02.000Z","likeCount":0},{"parentId":"Ugyn1rBN2cQjMpt8jtp4AaABAg","authorDisplayName":"Shalani Ish","replyComment":"@Samsung J4 ow oya hari","publishedAt":"2020-01-31T15:38:39.000Z","likeCount":1},{"parentId":"Ugyn1rBN2cQjMpt8jtp4AaABAg","authorDisplayName":"Shalani Ish","replyComment":"@Hjs Hhs 👍👍👍👍👍","publishedAt":"2020-01-31T15:34:04.000Z","likeCount":1},{"parentId":"Ugyn1rBN2cQjMpt8jtp4AaABAg","authorDisplayName":"Samsung J4","replyComment":"@Road life දැන්ද  දැක්කේ  bro","publishedAt":"2020-01-31T15:15:09.000Z","likeCount":0},{"parentId":"Ugyn1rBN2cQjMpt8jtp4AaABAg","authorDisplayName":"Road life","replyComment":"@Samsung J4 ay machan මට 😷😷 faces 2k එවලා thiyenne.. Hethuwa","publishedAt":"2020-01-31T15:05:10.000Z","likeCount":0},{"parentId":"Ugyn1rBN2cQjMpt8jtp4AaABAg","authorDisplayName":"Samsung J4","replyComment":"@Udiththara Madubashini 👍👍👌","publishedAt":"2020-01-31T12:58:29.000Z","likeCount":0},{"parentId":"Ugyn1rBN2cQjMpt8jtp4AaABAg","authorDisplayName":"Udiththara Madubashini","replyComment":"Ane ow apita wdak na anika apu nemene laginne ekine.ekita ewa thiyei apita mokatada kagewath ewa data kapan blnne.nahadichcha hadiyawak nathi  aya gana katha ona na","publishedAt":"2020-01-31T12:51:46.000Z","likeCount":0},{"parentId":"Ugyn1rBN2cQjMpt8jtp4AaABAg","authorDisplayName":"Samsung J4","replyComment":"@Samantha Kumari ඉරිසියාව සුද්දෝ   කෙටි වචනෙන් කියනවනම්","publishedAt":"2020-01-31T12:41:33.000Z","likeCount":0},{"parentId":"Ugyn1rBN2cQjMpt8jtp4AaABAg","authorDisplayName":"Samantha Kumari","replyComment":"@Samsung J4 ඔයා කියන එකත් ඇත්ත.එහෙනම් සැමියාට,බිරිදටපෙම්වතියට ,පෙම්වතාට ඒ විඩිහට ආමන්ත්‍රණය කරන එකත් ලොකු පවක්.මේ අය කියන විදිහට.","publishedAt":"2020-01-31T09:12:24.000Z","likeCount":0},{"parentId":"Ugyn1rBN2cQjMpt8jtp4AaABAg","authorDisplayName":"Samantha Kumari","replyComment":"@Samsung J4 ඔය උඩබුරන අය තමයි දවසක තමන්ගෙ මිනිහ හරි ගෑනි හරි ලොකු කරන් දෙවියන් වගෙ හිටපු දෙමාපියන්ට නොසලකා හරින්නෙ.මගෙනම් තත්ත නෑ තත්තට මං කරන්න තියන පිං කරනව.අම්ම ඉන්නෙත් මං ලග එයාට මං තමයි සලකන්නෙත්.ඒත් හැම අම්ම තත්තම එක වගේ නෑ දරුවොන්ට දෙමාපියන් එපා වෙන්න හේතු ඇති කියල හිතන්න බැරි අයනෙ ඉන්නෙ.අපි කොච්චර කීවත් සාධාරණ විදිහට හිතන්නෙ කීයෙන් කී දෙනාද","publishedAt":"2020-01-31T09:09:08.000Z","likeCount":0},{"parentId":"Ugyn1rBN2cQjMpt8jtp4AaABAg","authorDisplayName":"Samsung J4","replyComment":"@Samantha Kumari ....ගොඩක් අය කියනවා මගෙ මුලු ලොකෙම ඔයා ,, මගෙ පන ඔයා  ..එතකුට ai ehwata මොකුත් කියන්නේ නැත්තේ  ..","publishedAt":"2020-01-31T08:59:32.000Z","likeCount":0},{"parentId":"Ugyn1rBN2cQjMpt8jtp4AaABAg","authorDisplayName":"Samantha Kumari","replyComment":"@Shalani Ish 😁😁😁","publishedAt":"2020-01-31T08:56:46.000Z","likeCount":0},{"parentId":"Ugyn1rBN2cQjMpt8jtp4AaABAg","authorDisplayName":"Samantha Kumari","replyComment":"@Samsung J4 😁😁😁😁","publishedAt":"2020-01-31T08:56:00.000Z","likeCount":0},{"parentId":"Ugyn1rBN2cQjMpt8jtp4AaABAg","authorDisplayName":"Samantha Kumari","replyComment":"@Apsara Dilhani තුවාලෙ වෙදනාව දන්නෙ තුවාලෙ තියන කෙනානෙ අප්සරා .ඒක නොදන්න අය හිතන්නෙ හැම අම්ම තාත්තම එයාලගෙ අම්ම තාත්ත වගේමයි කියල","publishedAt":"2020-01-31T08:54:45.000Z","likeCount":1},{"parentId":"Ugyn1rBN2cQjMpt8jtp4AaABAg","authorDisplayName":"Samsung J4","replyComment":"@Samantha Kumari වැඩක්  නැහැ කියලා","publishedAt":"2020-01-31T08:53:47.000Z","likeCount":0},{"parentId":"Ugyn1rBN2cQjMpt8jtp4AaABAg","authorDisplayName":"Samantha Kumari","replyComment":"@Shalani Ish ඇත්ත කතාව.දරුවොන්ට බනින්න ගොඩක් අය ඉන්නව.එත් දෙමාපියන් එපා වෙන්න ඒ අය අතින්  ඒ ළමයින්ට වෙලා තියන අසාධාරණයකම් මොනාද කියල කවුරුත් දන්නෙ නෑනෙ.ඒ නිසා හැම දේකම දෙපැත්තක් තියනව කියල හිතන්න.වපුරන දේ තමයි ලැබෙන්නෙ.දැන් මට බනී කට්ටිය.ඒත් ඒ බනින අය පිලිනොගන්න ඇත්තත් ඒකමයි.","publishedAt":"2020-01-31T08:49:46.000Z","likeCount":0},{"parentId":"Ugyn1rBN2cQjMpt8jtp4AaABAg","authorDisplayName":"Sopna Aktar","replyComment":"Owe","publishedAt":"2020-01-31T08:00:39.000Z","likeCount":1},{"parentId":"Ugyn1rBN2cQjMpt8jtp4AaABAg","authorDisplayName":"Ronika frenando","replyComment":"Samsuntai mea kiyannea aaki moka akka budiya gaththata apita adala na aaki kelagannaaka akitai wadinnea ratea enna unta nemea aath presnea kelina aawa kela ganiyau hoatalkamara wala geval wala mokada yakoa aava fb dannea ballita lajja nadda hadena lamai ennawanea yakunea unuth balanawa meava demaupiyanta kisima garuthwayak na lajja bayak na thopita oannea thawth aa wagea asanwara samajayak hadannda monadea thibunath mathaka thiya ganiyau thaman karanapau pin thaman passea annea samajeta meavada thopea aadarsa","publishedAt":"2020-01-31T07:04:39.000Z","likeCount":0},{"parentId":"Ugyn1rBN2cQjMpt8jtp4AaABAg","authorDisplayName":"Samsung J4","replyComment":"@Samith Madushan එයා අම්මා, තාත්තාට  බැනලා නැහැ  ..බන්","publishedAt":"2020-01-30T15:55:20.000Z","likeCount":0},{"parentId":"Ugyn1rBN2cQjMpt8jtp4AaABAg","authorDisplayName":"Samith Madushan","replyComment":"Eki moka ekka hitiyath apita wedak na thamai. Eka eyage kamathta.  Eth amma thathtata banina 1 bihoma pahath wedak. Kaage unath  amma thathta e","publishedAt":"2020-01-30T15:37:21.000Z","likeCount":0},{"parentId":"Ugyn1rBN2cQjMpt8jtp4AaABAg","authorDisplayName":"Samsung J4","replyComment":"@Hjs Hhs darling","publishedAt":"2020-01-30T13:05:14.000Z","likeCount":0},{"parentId":"Ugyn1rBN2cQjMpt8jtp4AaABAg","authorDisplayName":"Samsung J4","replyComment":"@Hjs Hhs relax","publishedAt":"2020-01-30T13:04:46.000Z","likeCount":0},{"parentId":"Ugyn1rBN2cQjMpt8jtp4AaABAg","authorDisplayName":"Samsung J4","replyComment":"@Hjs Hhs really","publishedAt":"2020-01-30T13:04:18.000Z","likeCount":0},{"parentId":"Ugyn1rBN2cQjMpt8jtp4AaABAg","authorDisplayName":"Hjs Hhs","replyComment":"@Samsung J4 තරහ යනවා තමා අම්මා තාත්තට බනිනතොට කාගෙ හරි කැරියො","publishedAt":"2020-01-30T12:32:13.000Z","likeCount":3},{"parentId":"Ugyn1rBN2cQjMpt8jtp4AaABAg","authorDisplayName":"Hjs Hhs","replyComment":"@Samsung J4 තොගෙ පයියෙ  සයිස්  එක  මට මොකටද  තො එක  පෙන්නපන් අර තොට  පුක දෙන්න ආව අයට   කැරියො   තොපි වගෙ අම්මා තාත්තට  නැති උන්ට  මම බය වෙයිද   පොන්න  බල්ලා    අම්මෙක්ට  තාත්තා කෙනෙත්ට   අපහස කරලා මගෙ කටනම් වහනවා  බොරු  මට පෙන්නම බැරි  උන් තමා  තො   වගෙ  නුගත් උන්    උගත්නම්   දෙමව්පියන්ට  ගරහන්නෙ  බනින්නෙ නැ කැරියෙ","publishedAt":"2020-01-30T12:00:13.000Z","likeCount":1},{"parentId":"Ugyn1rBN2cQjMpt8jtp4AaABAg","authorDisplayName":"Hjs Hhs","replyComment":"@Samsung J4 මගෙ   අම්මට  වඩා  උබ   කිබ්  ලගටගියෙ  උන් දන්නවා අනික  මටත්උබගෙ අම්මට බනින්න පුලුවන්  එත්  මන් ආස නැ පව්  පුරවාගන්නයි   තො වගෙ එකෙක්නිසා එ අම්මට  බනින්නයි මොකද  මම    මාලිගාවෙ  ඉන්න අම්ටත්  වීදියෙ ඉන්නඅම්මටත් එක සමානව  ආද⁣ෙ කරන නිසා අනික තො වගෙ  ජරා  තත්වෙට මාත් වැටෙන්න       තවත් එකක්     බොසත් අම්මලාටත් පිසාචයො වගෙඋන් ඉපදෙනවා උබ වගෙ  පෙර  කරුමවල් වලට   මමනම්   දෙමව්පියන්ට  සලකන්නෙ   බුදුන්ටවගෙ එ නිසා තො වගෙ  පිසාචයෙක් නිසා  නිකන්මං මොකටද  පව්පුරවාගන්නෙ   සමනලයා","publishedAt":"2020-01-30T07:27:04.000Z","likeCount":1},{"parentId":"Ugyn1rBN2cQjMpt8jtp4AaABAg","authorDisplayName":"Hjs Hhs","replyComment":"@Samsung J4 කිබ්  පිසාචයා  කිබ්  වහලා   අසහන කාරයා   අම්මා අප්පා අදුරන්නෙ නැති එකා","publishedAt":"2020-01-30T04:58:13.000Z","likeCount":0},{"parentId":"Ugyn1rBN2cQjMpt8jtp4AaABAg","authorDisplayName":"Hjs Hhs","replyComment":"@Samsung J4   පිසාච්යා    කිබි  කන්නා","publishedAt":"2020-01-29T20:42:20.000Z","likeCount":2},{"parentId":"Ugyn1rBN2cQjMpt8jtp4AaABAg","authorDisplayName":"Hjs Hhs","replyComment":"@Samsung J4 මාරයි නෙද බං  උබ   උබ  අද්දැකිම  ගන්න  කරන්න ඔනි නැ බං උබලවගෙ   උන්   ඉද්දි  රටෙ  අනික   තොපි වගෙ  උන්  තසා අම්මා සහොදරයෙ අදුරන්නෙ   නැති උන්  අනික  බඩුවක්  තවත්  බඩුවක්ට  සපොට් කරනවා ඇර  උන්ට   බනින්නෙ නැ   තොපි වගෙ  උන්  ඉද්දි   ඉස්කොලෙ යන  පොඩ්  උනුත් දන්නවා   හැමදේම  ඇයි   තොපි වගෙ   පිසාචයෙ    නෙ  ඉන්නෙ  රටෙ  වැඩ්  පුර   කිබ් පිසාචයා","publishedAt":"2020-01-29T19:34:24.000Z","likeCount":1},{"parentId":"Ugyn1rBN2cQjMpt8jtp4AaABAg","authorDisplayName":"Hjs Hhs","replyComment":"@Samsung J4 කැමති උන් උඩ ඉන්නවනෙ   ලීක් කරගන්න  කරගනින් උන් එක්ක","publishedAt":"2020-01-29T16:02:02.000Z","likeCount":2},{"parentId":"Ugyn1rBN2cQjMpt8jtp4AaABAg","authorDisplayName":"Hjs Hhs","replyComment":"@Samsung J4 ඔයාට  වැරදිලා  ලීක්  කර ගන්න උන් තමා ඔය  දෙවල් වලට  හොද  කියන්නෙ   මටනම්  ලීක් කරගන්නවත්    ලීක් වෙන දෙවල් කරන්නවත් අදිස්සියක් නැ  එවා   හෙිද විදිහට  අම්මා  තාත්තාගෙ   සහොදරයන්ගෙ    කැමැත්තෙන් ලස්සනට දවසක  නිම වෙයි     මට  කිසිම අදිස්සියක්  නැ","publishedAt":"2020-01-29T14:45:07.000Z","likeCount":0},{"parentId":"Ugyn1rBN2cQjMpt8jtp4AaABAg","authorDisplayName":"Samsung J4","replyComment":"ඇයි බන් හින් මැණිකෝ කොල්ලොත් එක්ක ඔච්චර තරාහා ඔයාගේ එක්ක  ලික් කරාද කොල්ලෙක් 😐😐","publishedAt":"2020-01-29T12:55:51.000Z","likeCount":1},{"parentId":"Ugyn1rBN2cQjMpt8jtp4AaABAg","authorDisplayName":"Hjs Hhs","replyComment":"@Samsung J4 සිරියලතා නෙමෙයි  හිං මැනිකා ඇයි","publishedAt":"2020-01-29T12:41:54.000Z","likeCount":2},{"parentId":"Ugyn1rBN2cQjMpt8jtp4AaABAg","authorDisplayName":"Samsung J4","replyComment":"@Hjs Hhs appata siri සිරිය ලතාට තද උනාද ...😥😥","publishedAt":"2020-01-29T12:20:28.000Z","likeCount":1},{"parentId":"Ugyn1rBN2cQjMpt8jtp4AaABAg","authorDisplayName":"Hjs Hhs","replyComment":"@Samsung J4 පව් තො  තොපි වගෙ උන් මෙ පොලවට බරක් පයව් තොලොන්ච්  වෙලා   මෙ රට  මෙ පොව  දෙවම්පියන්ට  සමානයි  මච්  රට කියන්නෙ එතයි  ඉතිම්  දෙමව්පියන්ටත් නැති තොපි ගෙ පව් කාරයන් ඉන්න එක  හොද නැ මෙ රටෙ   පලයව්   තොලොන්ච් වෙලා","publishedAt":"2020-01-29T07:33:03.000Z","likeCount":1},{"parentId":"Ugyn1rBN2cQjMpt8jtp4AaABAg","authorDisplayName":"Hjs Hhs","replyComment":"@Samsung J4  උබ   ඉතිම්  දෙන  එකෙක්  නිසා   මගෙ  ඇත්ත  උබට පෙන ව්දිහ තමා ඔය","publishedAt":"2020-01-29T06:56:29.000Z","likeCount":1},{"parentId":"Ugyn1rBN2cQjMpt8jtp4AaABAg","authorDisplayName":"Hjs Hhs","replyComment":"@Shalani Ish 🤣🤣  බඩු  වෙච්ච උන්ට   අනිත්  උන්    ඇත්ත කියන  උන් සිල්ලර   පව්ල්  තමා  උබ  හරි","publishedAt":"2020-01-29T06:55:50.000Z","likeCount":0},{"parentId":"Ugyn1rBN2cQjMpt8jtp4AaABAg","authorDisplayName":"Samsung J4","replyComment":"@Shalani Ish 😂😂","publishedAt":"2020-01-29T06:45:53.000Z","likeCount":0},{"parentId":"Ugyn1rBN2cQjMpt8jtp4AaABAg","authorDisplayName":"Shalani Ish","replyComment":"@Samsung J4 kiyala wedak Neha.....sillara family 1","publishedAt":"2020-01-29T06:30:54.000Z","likeCount":3},{"parentId":"Ugyn1rBN2cQjMpt8jtp4AaABAg","authorDisplayName":"Samsung J4","replyComment":"@Hjs Hhs නොදකින් තොගේ හැදියාව පේනවා msg වලින්","publishedAt":"2020-01-29T05:45:09.000Z","likeCount":1},{"parentId":"Ugyn1rBN2cQjMpt8jtp4AaABAg","authorDisplayName":"Hjs Hhs","replyComment":"කාගෙ උනත් තාත්තා තාත්තා  තමා  මම  1000 ආවත්   හරිදෙට  වැරදි කියන්න  හරිනම්  මමඑ පැත්තෙ   අනික  හිවල්ලු  උඩබුරලන එක  නතර කරන්න   මට බැ මොකද   හද දැක්ක ගමන්  උන් ඔක්කොම  එකට  උඩබුරුලනවා    ම්නිහා   ලග  ඉද්දිද  තාත්තා  හොද නැති එකෙක් වෙන්නෙ  ඊට  කලින්  කියලා නැනෙ  කොහෙවත්   අනික   අම්මට  තාත්තටවත් නැති  උන්  තමා  උඩබුරුලන්නෙ   දැන් ඉන්ක උන්ට  ටකක් කෙලික් උනාම  ඔබාගන්න එකක් හරි  දාගන්න එකක් හරි  තිබ්බනම්   අම්මා  තාත්තා  දැරිවන්  ව්කුනාලා හරි ඒක කරගනි  එවාගෙ අවජාතක උන් තමා  මෙතන   උඩුබුරුලන්නෙ","publishedAt":"2020-01-29T05:30:04.000Z","likeCount":1},{"parentId":"Ugyn1rBN2cQjMpt8jtp4AaABAg","authorDisplayName":"Apsara Dilhani","replyComment":"Eka aththa eyata thaththage adare thiyena nathuwa athi a kathawe waradak dakunne na hamotama Amma thaththage innawa eth hamoma eka wage daruwanta adare na a adare eyage mahaththaya laga athi ithin eke waradak mokakda mamath mage ththathage  adare widinna thiya dakalawath na ithin apita thaththage wage watinne mahaththaya neda nodakapu kenekuta kohomada adare karanne","publishedAt":"2020-01-28T22:15:23.000Z","likeCount":3},{"parentId":"Ugyn1rBN2cQjMpt8jtp4AaABAg","authorDisplayName":"Samsung J4","replyComment":"@Road life 😷😷","publishedAt":"2020-01-28T15:16:36.000Z","likeCount":0},{"parentId":"Ugyn1rBN2cQjMpt8jtp4AaABAg","authorDisplayName":"Samsung J4","replyComment":"@Hjs Hhs ,,,,,,,eka ekige kemathta  eh kige taththa gana eki kiyanne anith ehunta ai ban kekkuma","publishedAt":"2020-01-28T14:33:54.000Z","likeCount":1},{"parentId":"Ugyn1rBN2cQjMpt8jtp4AaABAg","authorDisplayName":"Road life","replyComment":"@Shalani Ish හරි.,🤔","publishedAt":"2020-01-28T10:43:43.000Z","likeCount":2},{"parentId":"Ugyn1rBN2cQjMpt8jtp4AaABAg","authorDisplayName":"Hjs Hhs","replyComment":"දෙමව්පින්   හොද නැත්තෙ  කාටකාටත්   මිනිහෙක් ලගට  ගියාමයි  ගැනියෙක්  ලගට ගියාමයි    හැබැයි  එ දෙන්නා  කන්න බොන්න දෙනකන් හොදයි   අානන්ත පාප කර්මය කරගන්න  දෙමව්පියන්  මරන්නම  ඕනි නැ ගැරහෙව්වත් ඇති    අනික   කවදාවත්  බ්පු කිරිවල  නය ගෙවන්න බැ ජිව්ත කාලෙම සැලකුවත්      කිබ්බකටයි  පයියකටය්  වහල්  උනු වහලුන්ට ඒක තෙරෙන්නෙ නැ","publishedAt":"2020-01-28T10:06:38.000Z","likeCount":1},{"parentId":"Ugyn1rBN2cQjMpt8jtp4AaABAg","authorDisplayName":"Samsung J4","replyComment":"@Shalani Ish අනිවාර්යයෙන් සලනි","publishedAt":"2020-01-28T08:34:21.000Z","likeCount":1},{"parentId":"Ugyn1rBN2cQjMpt8jtp4AaABAg","authorDisplayName":"Shalani Ish","replyComment":"@Hjs Hhs daruwanta watinakamak denne nethi demaupiyanta daruwot watinakamak denne neha","publishedAt":"2020-01-28T08:26:01.000Z","likeCount":6},{"parentId":"Ugyn1rBN2cQjMpt8jtp4AaABAg","authorDisplayName":"Shalani Ish","replyComment":"Ow eaka etta","publishedAt":"2020-01-28T08:24:46.000Z","likeCount":0},{"parentId":"Ugyn1rBN2cQjMpt8jtp4AaABAg","authorDisplayName":"Hjs Hhs","replyComment":"එකි මොකා එක්ක හාට්යත් අපිට වැඩක් නැ    හැබැයි එකිට තාත්තට වඩා වට්න්නෙ එකා ක්ව්වමයි අපිටත්ට්කක් තරහා දෙමව්පියන්ට වඩා වට්න  දෙවල් නැ මෙ  ලොකෙ    එ්ක තෙරුම්  ගත්ත නැති හරක් තමා ඔය උඩ බුරන්නෙ","publishedAt":"2020-01-28T07:43:38.000Z","likeCount":2},{"parentId":"Ugyn1rBN2cQjMpt8jtp4AaABAg","authorDisplayName":"MALKANTHI JAYAKURU","replyComment":"Eka aththa..","publishedAt":"2020-01-27T20:25:40.000Z","likeCount":2},{"parentId":"Ugyn1rBN2cQjMpt8jtp4AaABAg","authorDisplayName":"Nishadika Sawwandi","replyComment":"Ane aththatama adare karana katawath apita baninna aithiyak na","publishedAt":"2020-01-27T14:52:07.000Z","likeCount":5}]},{"id":"UgxDPmkxQY7ttMJl0hZ4AaABAg","comment":"අනේ යකෝ අනිත් උන්ටත් කියන්න ඇත්තෙ ඔහොමම තමයි හර්ශන ඔයා පව් නේ🙃🙃 පිස්සු මුන්ට","author":"Ishani Ishani","likeCount":12,"totalReplyCount":0,"publishedAt":"2020-01-27T14:27:45.000Z","replies":[]},{"id":"UgyRTq-jXpfAvV2knSp4AaABAg","comment":"පර වෙිසියෝ","author":"Pathima Pathima","likeCount":1,"totalReplyCount":0,"publishedAt":"2020-01-27T14:25:59.000Z","replies":[]},{"id":"UgxubKK8IB_kvWlZzqV4AaABAg","comment":"නිදකින්  වෙසියො තොපිට  හෙනම ගන්නවා","author":"مليكا رر","likeCount":19,"totalReplyCount":2,"publishedAt":"2020-01-27T14:21:51.000Z","replies":[{"parentId":"UgxubKK8IB_kvWlZzqV4AaABAg","authorDisplayName":"Manori Perera","replyComment":"Ow","publishedAt":"2020-01-31T12:00:57.000Z","likeCount":0},{"parentId":"UgxubKK8IB_kvWlZzqV4AaABAg","authorDisplayName":"samanthi chandrica kiriella Nissanka","replyComment":"Sinhala liyagnn wath beri thambi katha karana vdiya.shik","publishedAt":"2020-01-31T10:40:12.000Z","likeCount":0}]},{"id":"UgwjlA-GrGKrNQfCjup4AaABAg","comment":"Maki patta baduwa.makita gama kollo polimak damma.gon hutti..patta wasi.aiyo muga paiyata .hoyanna bahath natiwai....","author":"Saman rajapaksha","likeCount":1,"totalReplyCount":5,"publishedAt":"2020-01-27T14:21:27.000Z","replies":[{"parentId":"UgwjlA-GrGKrNQfCjup4AaABAg","authorDisplayName":"Erini tumazo","replyComment":"@piumy amanda Aniwarenma","publishedAt":"2020-01-31T07:09:46.000Z","likeCount":0},{"parentId":"UgwjlA-GrGKrNQfCjup4AaABAg","authorDisplayName":"Sudusinghe Hashini uthpala","replyComment":"@piumy amanda👍👍👍","publishedAt":"2020-01-27T17:57:33.000Z","likeCount":2},{"parentId":"UgwjlA-GrGKrNQfCjup4AaABAg","authorDisplayName":"Tekla Dilrukshi","replyComment":"@piumy amanda 👌👌👌","publishedAt":"2020-01-27T16:30:57.000Z","likeCount":2},{"parentId":"UgwjlA-GrGKrNQfCjup4AaABAg","authorDisplayName":"Nishadika Sawwandi","replyComment":"@piumy amanda Aniwaranma","publishedAt":"2020-01-27T14:51:06.000Z","likeCount":2},{"parentId":"UgwjlA-GrGKrNQfCjup4AaABAg","authorDisplayName":"piumy amanda","replyComment":"Me gani moka hare...aulak na....ganiyekta ohoma agilla dik karala Hagi Hangi banina Un innawa neda...anna Un tamai Ganu..anna unatai Andawanna ona..Chithta genalla...Munata gihilla...banapiyako....banala..ewa oppu karapalla....ohoma hangi hangi.banina kam....konda pana nathi pirimi..😬😬😬👎👎👎👎👎👎👎👎👎👎👎👎👎👎👎👎👎.Heta Ubage ammata...akkata...Nangita..Nandata...oya unage gani innawa nam..ganita..duwata...oya wage dewal ahanna wei heta dawase de...eka hinda ewa danan jiwath weyalla...buruwooo","publishedAt":"2020-01-27T14:28:02.000Z","likeCount":5}]},{"id":"UgyGjiIWjPdKP1v4Yq54AaABAg","comment":"ඔහොම කලින් කෙනාටත් කියන්න අති .","author":"Village life","likeCount":3,"totalReplyCount":0,"publishedAt":"2020-01-27T14:16:00.000Z","replies":[]},{"id":"UgzuB1S2_aoCieN_yhl4AaABAg","comment":"Volga marry karanna..inna kena wenna athi oya..ithin apita mokada...eyage kalin Husbad wena kenik marry karanna ne yanne....ithin Uth ehema Una kiyala..volga thaniyama inna onada...kawama hare marry karanna epai...Moda.Gon..Harak..Buruwo Lankawe inne...katama hare katha hadanna Tamai balan inne..Lankawe minissunta wena wedak nadda...😬😬😬😬😬😬😬😬😬👎👎👎👎👎👎👎👎👎👎👎👎👎👎👎👎","author":"piumy amanda","likeCount":15,"totalReplyCount":0,"publishedAt":"2020-01-27T14:05:58.000Z","replies":[]}]}]