[{"channelId":"UCs_mHlm5_C82W5WCIJaSMbQ","publishedAt":"2018-03-27T15:25:53.000Z","title":"ලංකාවේ ගණං වැඩිම නිළියෝ 5 දෙනා මෙන්න - Sri Lanka's Highest-Paid Music Video Actress","description":"Sri Lanka's Highest Paid Music Video Actress. \n\nIraj's \"ආශාවරී | Ashawari\" actress Oshadi Himasha has been named Sri Lanka's highest-paid music video actress. Teena Shanell Fernando was runner-up. Piumi Hansamali has claimed the third place.\n\nThanks for watching this video and make sure you share the video with your friends and don't forget to subscribe.","viewCount":"1083718","likeCount":"1542","dislikeCount":"574","commentCount":"182","tags":["Actress","Srilanka","Music Video","Iraj","Ashawari","Oshadi Himasha","Teena Shanell","Piumi Hansamali","Wassane Hine","පියුමි හංසමාලි","අමන්දා සිල්වා","Amanda Silva","Piumi Srinayaka"],"thumbnailUrl":"https:\/\/i.ytimg.com\/vi\/V_acUujBOZw\/hqdefault.jpg","category":"SG","sentiment":"N","comments":[{"id":"UgxAQDMY_3v8Z2kh-XB4AaABAg","comment":"Pala pakayo yanna","author":"Asela Disanayaka","likeCount":0,"totalReplyCount":0,"publishedAt":"2020-02-22T04:15:37.000Z","replies":[]},{"id":"UgzSrfRoptD0uBehlvp4AaABAg","comment":"Ganikawo tika","author":"Asela Disanayaka","likeCount":1,"totalReplyCount":0,"publishedAt":"2020-02-22T04:13:54.000Z","replies":[]},{"id":"UgxCuYI-yOCeqTpATiN4AaABAg","comment":"Yako enda enda gana aduwenawane mona ponnayek da uba","author":"Sandaru harsha","likeCount":0,"totalReplyCount":0,"publishedAt":"2020-01-30T09:25:09.000Z","replies":[]},{"id":"Ugw7in2gQ4TH5rRMli94AaABAg","comment":"Mun patta wesiyo","author":"wimala w Singer","likeCount":0,"totalReplyCount":0,"publishedAt":"2020-01-26T14:20:49.000Z","replies":[]},{"id":"Ugxu_-OmW9b0XC7J87d4AaABAg","comment":"ඔවුන් නිළියෝද පට්ට වේසා ගොන් බඩු වලට නිලියෝ කියන්න ලැජ්ජයි බන් ගනිකවන්ටත් වඩා අන්තයි මේ බඩු වෙසවියෝ දකිනකොතත් අප්පිරියයි 🤮🤮🤮🤮🤮🤮🤮🤮🤮🤮🤮🤮🤮🤮🤮","author":"Sanjeewa makase","likeCount":3,"totalReplyCount":0,"publishedAt":"2020-01-26T10:31:14.000Z","replies":[]},{"id":"UgylT-gkNAStQPTDpCV4AaABAg","comment":"Pake niliyo gonbadu","author":"hemantha bandara","likeCount":0,"totalReplyCount":0,"publishedAt":"2020-01-25T18:55:57.000Z","replies":[]},{"id":"Ugz_LffAluRIRCFR4ed4AaABAg","comment":"https:\/\/youtu.be\/G9jFSRQv8ZE","author":"amazing world","likeCount":0,"totalReplyCount":0,"publishedAt":"2020-01-25T15:57:52.000Z","replies":[]},{"id":"UgxX0httAVHYjxw1wOd4AaABAg","comment":"අවංක කාන්තාවක් කතා කරන්නImo 0759904558","author":"rukmalgunarathna Rukmalgunarathna","likeCount":0,"totalReplyCount":0,"publishedAt":"2020-01-23T12:36:27.000Z","replies":[]},{"id":"UgzsRiP62TE5s1O3rdx4AaABAg","comment":"Good luck....nevet charge less....i feel like what their charging  is  very less....","author":"ajith fernando","likeCount":0,"totalReplyCount":0,"publishedAt":"2020-01-23T08:55:21.000Z","replies":[]},{"id":"Ugw83ypq8_LmOQnQrtV4AaABAg","comment":"මෙි ලංකාවෙ තඩි ගොන්නු රංජා  ඇරියෙ ටිනාට නේ, රංජ ඇරියෙ පුකේ,","author":"Jayawardana Malwennage","likeCount":0,"totalReplyCount":0,"publishedAt":"2020-01-20T15:49:35.000Z","replies":[]},{"id":"UgwvqCaHpj6xChRwBVR4AaABAg","comment":"Mun kohomada niliyo wenne.shik.","author":"nadithi nulara","likeCount":0,"totalReplyCount":0,"publishedAt":"2020-01-20T08:48:03.000Z","replies":[]},{"id":"UgxGUE8JZO4Y-L7vGwF4AaABAg","comment":"Mon.ganikawo.kesima.sanwara.adumak.adinawada.monta.ammala.thththala.enna.awnda.aga.aeiyedagena.sinhalakamatath.lajjayi.","author":"Menike Ugd","likeCount":0,"totalReplyCount":0,"publishedAt":"2020-01-18T08:13:46.000Z","replies":[]},{"id":"UgwDxv7wqBZGUwQkXdx4AaABAg","comment":"Owa nekan dunnat apoooooo","author":"Kumari Albaha","likeCount":0,"totalReplyCount":0,"publishedAt":"2020-01-16T16:31:34.000Z","replies":[]},{"id":"Ugw1b6O_GsPiw02d4X14AaABAg","comment":"Tuuuu gon waseyooo","author":"Kumari Albaha","likeCount":0,"totalReplyCount":0,"publishedAt":"2020-01-16T16:30:35.000Z","replies":[]},{"id":"UgyKW2Q7nsyp45M6CC14AaABAg","comment":"Lassanama godak aadare niliya malani meyal niliyoda","author":"Mali Mali","likeCount":0,"totalReplyCount":0,"publishedAt":"2020-01-15T07:11:48.000Z","replies":[]},{"id":"UgzzFdTMI8uWv6uOhDJ4AaABAg","comment":"මෙයාල නිලියොද? 😂😂😂","author":"dilini malika","likeCount":0,"totalReplyCount":0,"publishedAt":"2020-01-13T10:28:27.000Z","replies":[]},{"id":"UgykBsiz_ITOi5_mE754AaABAg","comment":"රන්ජන්ගේ තවත් වීඩියෝවක් ලීක් වෙයි . \nhttps:\/\/youtu.be\/UwkxM85ZGoc","author":"NC TV - හොට්‌ ගොසිප්","likeCount":0,"totalReplyCount":0,"publishedAt":"2020-01-12T05:24:18.000Z","replies":[]},{"id":"UgzWMjNdUppXaUKz-2l4AaABAg","comment":"Huththa raththaran valindha??","author":"Sikkander MM","likeCount":0,"totalReplyCount":0,"publishedAt":"2020-01-11T11:28:45.000Z","replies":[]},{"id":"UgypeswkE8sAnJYLytB4AaABAg","comment":"වැඩියෙන්ම අය කරනවා කිවුවේ රගපාන්නද?..👌","author":"Nilanthi Fernando","likeCount":0,"totalReplyCount":0,"publishedAt":"2020-01-11T08:19:50.000Z","replies":[]},{"id":"UgzMPKSaCANiWQuWY0V4AaABAg","comment":"ඇඟ  එළියේ   gana.serai...ane   ලංකාවට   ගිය  කල...මේ...balliyo  නිසා ....tu.tu....","author":"Troncy Kadana","likeCount":0,"totalReplyCount":0,"publishedAt":"2019-12-21T18:16:28.000Z","replies":[]},{"id":"UgwhFi4I_2NIGF06ZlV4AaABAg","comment":"Niruwatha eliye danavanam  salli thamayi .Ane ammapa ape ratata giya kala","author":"Marie Dilukshi","likeCount":0,"totalReplyCount":0,"publishedAt":"2019-12-06T06:25:58.000Z","replies":[]},{"id":"UgyAgfsO4HcL59Vt1lZ4AaABAg","comment":"https:\/\/youtu.be\/O50oRl6Nu9o ‌මේවගේ වටිනා වීඩියෝ එකක් බලලා SUBSCRIBE එකක් ‌දෙන්න කැමති නැද්ද? 👌🤩🤩","author":"My best","likeCount":0,"totalReplyCount":0,"publishedAt":"2019-11-23T09:00:57.000Z","replies":[]},{"id":"Ugzr7NXqS2RMmFiIQCB4AaABAg","comment":"Munge than 2 ka balapan loku   mun habei badu  mekap eka thiyenne","author":"Udula Viduranga","likeCount":0,"totalReplyCount":0,"publishedAt":"2019-11-17T16:08:25.000Z","replies":[]},{"id":"UgyIwHQEKNlSS9ifS694AaABAg","comment":"thy are hottest and so sexy","author":"Sweet Girls","likeCount":0,"totalReplyCount":0,"publishedAt":"2019-11-14T15:17:22.000Z","replies":[]},{"id":"UgyK_7h3I-g3CEC-XpB4AaABAg","comment":"වේස බඩු මිවුසික් විඩියො වලට යොදාගන්නැතිව අර අහිංසක දුප්පත් මිනිස්සුන්ව ඔවට අරගෙන එ මිනිස්සුන්ට සල්ලි දිපන් බන් වේසා හුත්තියන්ව අරගෙන උන්ට සල්ලි බෙදන්නැතුව..නැත්නම් ඔය සල්ලි බෙදපන් කන්න අදින්න නැති දුප්පතුන්ට ලොකු පිනක්..අද කාලේ මෙ රටෙ කතා වෙන්නෙම වේසා හුත්තියන් ගැනනෙ චික් මෙහෙමත් රටක් යකො","author":"Pathum Vlogs","likeCount":0,"totalReplyCount":0,"publishedAt":"2019-11-01T12:48:42.000Z","replies":[]},{"id":"Ugw-w4Yjc-GKfshGpxt4AaABAg","comment":"mama loku vela piumi akki ekkai, teena akki ekkai, oshadi akki ekkai, chulakshi akki ekkai sex karanna hitan inne, eth itin music video ekakata laksha 2 gannava nan sex karanna laksha 10 vath one kiyai ! kamak na, mama loku vela eta vada lassana girlslava hoyagena sex karanava","author":"Danitha zoyza","likeCount":0,"totalReplyCount":0,"publishedAt":"2019-09-22T07:07:41.000Z","replies":[]},{"id":"UgySxqzepmRGfOuP3VF4AaABAg","comment":"මේ රටේ දුප්පත් අසරන මනුෂ්‍යයන් කොපමණක් ඇත්ද ඔය හිකනිලියන්ට දෙන සල්ලි වලින්  එ   මනුෂ්‍යයන්ට පිහිට උනා නම් එක තමා වටින්නේ මහත්තයෝ  මේවා කීවාට වැඩක් වෙන්නේ නැ","author":"Gayan Harsha","likeCount":0,"totalReplyCount":0,"publishedAt":"2019-09-17T22:00:15.000Z","replies":[]},{"id":"UgyNoX62yECaBOJ4sf94AaABAg","comment":"මේ රටේ දුප්පත් අසරන මනුෂ්‍යයන් කොපමණක් ඇත්ද ඔය හිකනිලියන්ට දෙන සල්ලි වලින්  එ   මනුෂ්‍යයන්ට පිහිට උනා නම් එක තමා වටින්නේ මහත්තයෝ  මේවා කීවාට වැඩක් වෙන්නේ නැ","author":"Gayan Harsha","likeCount":0,"totalReplyCount":0,"publishedAt":"2019-09-17T22:00:11.000Z","replies":[]},{"id":"UgxmtIBX-UM62pwOG5p4AaABAg","comment":"Ganan wadima pukatada huththatada","author":"Sukman Tamang","likeCount":0,"totalReplyCount":0,"publishedAt":"2019-09-16T18:15:19.000Z","replies":[]},{"id":"Ugza-Q9yuGdhvXLhPh54AaABAg","comment":"අනෙ රුපියල් 100ක් වටින්නැ මුංව","author":"Nilanthi Dewage","likeCount":0,"totalReplyCount":0,"publishedAt":"2019-08-03T02:45:58.000Z","replies":[]},{"id":"UgyplETbTPnMA93UndV4AaABAg","comment":"Kunu hagawal wala mecup gahagena giye naththam kunugodak thamai.....","author":"Deepani Mangalika","likeCount":0,"totalReplyCount":0,"publishedAt":"2019-08-02T13:25:07.000Z","replies":[]},{"id":"Ugx11WlSrNbtPKXlUaZ4AaABAg","comment":"හරිම ප්‍රයෝජනවත් විඩියෝ එකක් දිගින් දිගටම මේ වගේ කරන්න බුදු සරණයි 😌😌","author":"dulaj pahasara","likeCount":0,"totalReplyCount":0,"publishedAt":"2019-08-02T11:02:26.000Z","replies":[]},{"id":"UgwN3sbuWzv74Q_KNV14AaABAg","comment":"යකෝ මේ  බඩුනෙ හුත්තො","author":"Antha Hem","likeCount":0,"totalReplyCount":0,"publishedAt":"2019-08-01T16:08:58.000Z","replies":[]},{"id":"UgzXAiVpDrjWa06RBlh4AaABAg","comment":"mun hodai hanaka wadata yawanna 🖕🖕🖕🖕🖕😆","author":"umantha adittiya","likeCount":0,"totalReplyCount":0,"publishedAt":"2019-08-01T13:02:19.000Z","replies":[]},{"id":"UgwNuoQgAy5fL_dPV_94AaABAg","comment":"Mun niliyo BOLA WAGE PONNAYANTA...🤩🤩🤩🤩🤩","author":"Bimalka Lahiru","likeCount":0,"totalReplyCount":0,"publishedAt":"2019-08-01T00:00:39.000Z","replies":[]},{"id":"Ugwn202g_ajypVqUcNl4AaABAg","comment":"Mun tika badu sat aka nati beri un","author":"Roshan Samsudeen","likeCount":0,"totalReplyCount":0,"publishedAt":"2019-07-31T16:41:33.000Z","replies":[]},{"id":"UgzBFbkXVwcDPJ7OOA94AaABAg","comment":"boru daanna epa bn echchara ganne naaa ...","author":"Vithanage Gihan","likeCount":0,"totalReplyCount":0,"publishedAt":"2019-07-30T09:18:24.000Z","replies":[]},{"id":"UgyREAjy6LrOfWh7GVZ4AaABAg","comment":"උබට පිස්සුද යකෝ මේ ගණිකාවන්ට නිලියො කියන්න 😂😂😂😂","author":"Yohan Madhushanka","likeCount":6,"totalReplyCount":0,"publishedAt":"2019-07-29T05:07:36.000Z","replies":[]},{"id":"Ugx0MqI7_-WCaC3TWYZ4AaABAg","comment":"ඉක්මනින් ශුක්රාණු පිට වෙනවද? ලිංගයේ ප්ර්මාණය ගැන සැහිමකට පත් නොවේද ?\n@prFw","author":"Rathu Satahana","likeCount":0,"totalReplyCount":2,"publishedAt":"2019-07-29T04:34:10.000Z","replies":[{"parentId":"Ugx0MqI7_-WCaC3TWYZ4AaABAg","authorDisplayName":"Kiya Yapa","replyComment":"Gon badu","publishedAt":"2019-09-14T08:20:39.000Z","likeCount":0},{"parentId":"Ugx0MqI7_-WCaC3TWYZ4AaABAg","authorDisplayName":"Wasantha Ukwaththage","replyComment":"Rathu Satahana","publishedAt":"2019-07-29T07:04:46.000Z","likeCount":0}]},{"id":"UgzDs6J6eZ7RWunPyH94AaABAg","comment":"😈😈😈😈","author":"s.s v sadun viraj","likeCount":0,"totalReplyCount":0,"publishedAt":"2019-07-28T15:24:31.000Z","replies":[]},{"id":"Ugw6ssQ7q2P1qZ9iuz94AaABAg","comment":"ඉරාජ්ට පිංදෙන්න බඩු ටික ගොඩ ගියා...","author":"මදීන් Di රස්තා","likeCount":10,"totalReplyCount":1,"publishedAt":"2019-07-28T11:52:37.000Z","replies":[{"parentId":"Ugw6ssQ7q2P1qZ9iuz94AaABAg","authorDisplayName":"Madushan Sampath","replyComment":"😅😅😅😅😅","publishedAt":"2019-11-26T18:57:36.000Z","likeCount":0}]},{"id":"Ugx0ASeyOjI8PgMA5eZ4AaABAg","comment":"පිටරට ෆිල්ම් කට ඇරන් බලන්න හොද යි හෙලුවෙන් නටන එව. ලන්කවෙ උනොත් අවුල්. පකෙ ලොජික් ලන්කවෙ උන්ගෙ","author":"Lilttle Fire","likeCount":0,"totalReplyCount":0,"publishedAt":"2019-07-28T03:07:53.000Z","replies":[]},{"id":"UgxZQhO-hec3B6BHTMt4AaABAg","comment":"1:50 that baduwa","author":"ma sen","likeCount":0,"totalReplyCount":0,"publishedAt":"2019-07-27T17:29:32.000Z","replies":[]},{"id":"Ugxb3LKu3hAoxiLuMSd4AaABAg","comment":"0:16 lovely sister . Love you dear","author":"ma sen","likeCount":0,"totalReplyCount":0,"publishedAt":"2019-07-27T17:28:01.000Z","replies":[]},{"id":"UgzRzFQSvNSVIkmVll54AaABAg","comment":"Hahahahahaha.. 😂😂😂 මුන් නිලියො??? හිනස්සන්න එපා බන්..","author":"Hasha Sandz","likeCount":1,"totalReplyCount":0,"publishedAt":"2019-07-27T16:33:53.000Z","replies":[]},{"id":"UgzYXNyhUDq1hIaszPB4AaABAg","comment":"දැන් නිළියන්ට බැනලා වැඩක් නැහැ වැරැද්ද තියෙන්නෙ අපි අතේ මොකද අපි ඒව බලන නිසයි ඒ අය මේ තරම් මාකට් වෙන්නේ අපි බලන එක නැවැත්තුවොත් නිකංම ඒ ගොල්ලො ඇදවැටෙනවා මං වැරැද්ද අපි අතේ කියලා කිව්වේ ඕක පටන් ගත්ත මුල්ම දවසෙ තමයි අපිට විරුද්ධ වෙන්න තිබ්බෙ මම නම් ඒ අයගේ කිසිම හොඳ වීඩියෝ එකක් දැකලා නැහැ සමාජෙට කියලා වැඩක් වෙන දෙයක් නම් දැකලා නැහැ","author":"amila amila","likeCount":9,"totalReplyCount":0,"publishedAt":"2019-07-27T15:12:16.000Z","replies":[]},{"id":"UgwNcj4TTkR7QMuAyYd4AaABAg","comment":"Sex","author":"Sharada Anjan","likeCount":0,"totalReplyCount":0,"publishedAt":"2019-07-27T08:10:22.000Z","replies":[]},{"id":"UgxgLR34MgVBVDJRix14AaABAg","comment":"මං හිතුවෙ පියුමි හන්සමාලි රුපියල් දෙදාහක්  ක් විතර ගන්නේ කියලා එක පාරකට😃😃😃😃😃😃","author":"nimesh nimesh","likeCount":7,"totalReplyCount":0,"publishedAt":"2019-07-26T18:46:06.000Z","replies":[]},{"id":"Ugzqi09Fv4WvG0M9BnR4AaABAg","comment":"Prodstitutes","author":"Jason Hill","likeCount":0,"totalReplyCount":0,"publishedAt":"2019-07-25T17:43:21.000Z","replies":[]},{"id":"Ugwbvxb_tw_fyQG0lIt4AaABAg","comment":"IS IT FOR ACTING OR NIGHT PARKING.?","author":"Dad Somaweera","likeCount":0,"totalReplyCount":2,"publishedAt":"2019-07-25T07:41:18.000Z","replies":[{"parentId":"Ugwbvxb_tw_fyQG0lIt4AaABAg","authorDisplayName":"Dad Somaweera","replyComment":"@Chandima Gunasena THANKS","publishedAt":"2019-07-25T14:28:53.000Z","likeCount":0},{"parentId":"Ugwbvxb_tw_fyQG0lIt4AaABAg","authorDisplayName":"Chandima Gunasena","replyComment":"😁😁😨👍","publishedAt":"2019-07-25T13:49:17.000Z","likeCount":0}]},{"id":"Ugx-J8hC6nfzF5vMBMl4AaABAg","comment":"https:\/\/youtu.be\/XbBQfzZPi2I\n\n🇱🇰 🇱🇰 🇱🇰 🇱🇰 🇱🇰 🇱🇰 Sri lanka 🇱🇰 🇱🇰 🇱🇰 🇱🇰 🇱🇰 🇱🇰","author":"Tharanga Damith","likeCount":0,"totalReplyCount":0,"publishedAt":"2019-07-25T03:10:50.000Z","replies":[]},{"id":"UgxdntUjAm6s7FRVj7t4AaABAg","comment":"🤡🤡🤡","author":"Luci Fernando","likeCount":0,"totalReplyCount":0,"publishedAt":"2019-07-24T20:32:49.000Z","replies":[]},{"id":"Ugx4YbUhiYq4DBThDlt4AaABAg","comment":"සල්ලි දෙනවා කිව්වොත් ඕකුන් පුකෙත් අරියි","author":"Buddika Madushan","likeCount":5,"totalReplyCount":0,"publishedAt":"2019-07-24T00:48:33.000Z","replies":[]},{"id":"Ugx4UnS70pKICV9iZwF4AaABAg","comment":"Mun niliyoda? Badune halo","author":"Dhanu shishi","likeCount":1,"totalReplyCount":0,"publishedAt":"2019-07-23T18:03:27.000Z","replies":[]},{"id":"UgyBjUqKgClkZRuGBmx4AaABAg","comment":"Ganu lamayekta thyenna ona sanvarakama vikunala ganna salii Mona magulak karannda halo. Mala vikara.😎😎😎😎😈😈","author":"Thuhini Mihirangi","likeCount":2,"totalReplyCount":0,"publishedAt":"2019-07-22T11:00:11.000Z","replies":[]},{"id":"Ugwlr8b1w5DUoPI0J9d4AaABAg","comment":"Apo wadak na niruwatha pennala ganna koti ganakata wadiya duk mahnsiyen wadagath vidihata hamba kara ganna eka rupiyal watinava😊","author":"Umalka Malshani Umalka Malshani","likeCount":5,"totalReplyCount":0,"publishedAt":"2019-07-20T10:22:13.000Z","replies":[]},{"id":"UgwvQoSxgu6dN7DUhFp4AaABAg","comment":"Appatahudu","author":"Sameera Ruwanthika","likeCount":0,"totalReplyCount":0,"publishedAt":"2019-07-19T13:34:19.000Z","replies":[]},{"id":"UgzZwkpG9r7fbcV4mvR4AaABAg","comment":"api maseta රුපියල් 20000 hynna tyna amruwa dnne api vthri akth office ake night weda krth","author":"Yelani Umalka","likeCount":0,"totalReplyCount":0,"publishedAt":"2019-07-18T17:47:11.000Z","replies":[]},{"id":"UgzhCZUCTYrbmBA93e14AaABAg","comment":"Nodakin huttiyo ubala urana wada nisa hodata inna ekatath lajjawa","author":"Lakshani Lakshani","likeCount":0,"totalReplyCount":0,"publishedAt":"2019-07-15T15:17:55.000Z","replies":[]},{"id":"Ugwf3wcXGeayUT5eOZ14AaABAg","comment":"ou ithin lankawe inna kupadi ganu 5 denane. ganan wennatha ithin.","author":"Sp Pradeep","likeCount":2,"totalReplyCount":0,"publishedAt":"2019-07-15T14:50:27.000Z","replies":[]},{"id":"UgycSp2hdJopc9f5suJ4AaABAg","comment":"නිරුවත  ලොකයෙම   දකිනවා  ...තම ස්වාමි පුරුශයාට  ලැබෙන්නෙ  හපේ තමයි..අනේ  සල්ලි🙂🙂🙂.","author":"Annet Jayasinghe","likeCount":19,"totalReplyCount":1,"publishedAt":"2019-07-15T10:23:21.000Z","replies":[{"parentId":"UgycSp2hdJopc9f5suJ4AaABAg","authorDisplayName":"Sampath Sampath","replyComment":"Sex","publishedAt":"2020-01-26T18:59:30.000Z","likeCount":0}]},{"id":"UgwQAHpZ-zxTbe9k9gp4AaABAg","comment":"පියුමිව දකිද්දි බඩ දගලනවා.","author":"Swarna Fernando","likeCount":15,"totalReplyCount":0,"publishedAt":"2019-07-14T12:01:22.000Z","replies":[]},{"id":"UgxYbZE2llrsHk96V3h4AaABAg","comment":"Piumi kohoma unat.. Hitha Hoda ganiyek","author":"Darshana Jayasinha","likeCount":1,"totalReplyCount":0,"publishedAt":"2019-07-11T04:38:43.000Z","replies":[]},{"id":"UgysUYcjQpqMhY_86fB4AaABAg","comment":"Nodakin witharak ,mama hithue mun laksha 20k withara gannawa giyala.","author":"Dilip Janaka","likeCount":1,"totalReplyCount":0,"publishedAt":"2019-07-08T08:52:49.000Z","replies":[]},{"id":"UgzEvYhppD4iWS64VMB4AaABAg","comment":"Me okkoma itin ape ayane a nisa katawahn innwa wena jathiyka una nm wadiya oni ne Muslim una nm amboo comment 500th melahata pannla tiyei","author":"Tashini Kawindya","likeCount":0,"totalReplyCount":0,"publishedAt":"2019-07-04T19:34:10.000Z","replies":[]},{"id":"UgzqePVV3R3pkSlfmld4AaABAg","comment":"Ma....Aya....Sadachar aya...kalassanno","author":"Sirilanka Kuwait","likeCount":0,"totalReplyCount":0,"publishedAt":"2019-05-30T19:10:58.000Z","replies":[]},{"id":"Ugwy1_cB5WHFzBLyZZ54AaABAg","comment":"මූන්ටවැහි.නැති.හෙන.වැදියන්","author":"Padminisalam Dalam","likeCount":1,"totalReplyCount":0,"publishedAt":"2019-04-21T12:17:25.000Z","replies":[]},{"id":"UgxnvDOc0Ozofy1RWrZ4AaABAg","comment":"Mas kellak mechchara gananda Yahoo","author":"Suranga Silva","likeCount":0,"totalReplyCount":0,"publishedAt":"2019-04-16T19:59:35.000Z","replies":[]},{"id":"UgzN17DT1NZYU_ySqS94AaABAg","comment":"අපේ සුපිරි ක්‍රිකට් තරු සහ ඔවුන්ගේ සුරූපී බිරියන්...          https:\/\/youtu.be\/wFtO9oXQIKg","author":"කැඩපත # 1","likeCount":2,"totalReplyCount":0,"publishedAt":"2019-04-16T02:44:23.000Z","replies":[]},{"id":"UgyWenhjIf-1tXaPtPd4AaABAg","comment":"lankawe dan inna hodama gonnu set eka mun tama.oka neme munge job eka minissu ekka yana eka","author":"Chathura Pieris","likeCount":2,"totalReplyCount":0,"publishedAt":"2019-04-15T06:59:32.000Z","replies":[]},{"id":"UgwzYTYPenVNmu0T05V4AaABAg","comment":"Unge kimbawal raththaranda.","author":"Lahiru Madhawa","likeCount":0,"totalReplyCount":0,"publishedAt":"2019-04-10T14:49:02.000Z","replies":[]},{"id":"UgxdBtHfBbgUrekz78R4AaABAg","comment":"kamati akkiyak anna habai boruwat newai 0781308298","author":"Chandana Bandara","likeCount":0,"totalReplyCount":0,"publishedAt":"2019-04-02T16:13:54.000Z","replies":[]},{"id":"UgyV_q-yDx-DpZ6z2dN4AaABAg","comment":"දැන් ලන්කවෙ කතා වෙන්නෙම මෙ නිලියන් ගැනයි කුඩු මුදලලිල ගැනයි වෙන දෙයක් ඇත්තෙම නැ තව ඉස්සරහට යත්දි අපෙ රටට මොනව වේයිද","author":"Saman Dammika","likeCount":16,"totalReplyCount":0,"publishedAt":"2019-03-29T06:17:56.000Z","replies":[]},{"id":"UgxphGAdvZEblt3_VPt4AaABAg","comment":"මුන් කොටියක් ගත්තත් අපිට මොකද බන් වැකකට ඇති දෙයක් දපල්ල බන් මෙ වගෙ වල්පල් දන්නෙ නැතුව බොලත් මුන් ගැන කත කරනව හැමදම වැකක්නැ වගෙ බොලටත් නිකමට කියහල්ල දැන් බලන්න අපෙ ක්‍රිකට් කන්ඩයමෙ ඉන්න කොල්ලො ගැන හරියකට tv චැනල් එහෙකින් වත් කත කරනවද කියල මැච් එකක් තියෙන කලෙට අපෙ කොල්ලො ගැන කත කරනව හරියට නිකන් හව හද දකින්න වගෙ බොල මේ නිලියන් ගැන හැමදම දවසට එක ගනෙ ව්ඩියො දනව බොරුද මම කියන්නෙ ලන්කවෙ ඉන්න යුටියුබ් චැනල් වලටයි tv චැනල් වලටයි අපෙ ක්‍රිකට් ගහන කොල්ලො මතක් වේන්නෙ මැච් එකක් යනකොට ව්තරයි ඉට පස්සෙ උන් ගැන කිසිම දෙයක් නැ බොලටත් වැඩක් නැත්තම් දන්නම දෙයක් නැත්තම් ව්ඩියො නොද ඉදපල්ල මෙවගෙ වැඩක් නැති ව්ඩියො දන්නෙ","author":"Saman Dammika","likeCount":0,"totalReplyCount":0,"publishedAt":"2019-03-29T06:16:16.000Z","replies":[]},{"id":"UgySGPn0aAN9MKiHBsB4AaABAg","comment":"aneee munge gana munge eka vikunanwa salli wlata","author":"Keshi නිරෝ keshi නිරෝ","likeCount":0,"totalReplyCount":0,"publishedAt":"2019-02-19T21:40:05.000Z","replies":[]},{"id":"Ugy6f_uoi93qgJMdsWV4AaABAg","comment":"sub kala saha lik 674 magen.apiwath sub karala sup ekak denna.sub saha lik dena channel walata sub,lik aniwa apen.theruwan saranai","author":"NethRoo Productions","likeCount":1,"totalReplyCount":0,"publishedAt":"2019-02-18T15:49:17.000Z","replies":[]},{"id":"UgwJOsDms2FBQ7Jo6jJ4AaABAg","comment":"අප්පට සිරි මුන් හිතන් ඉන්නවද දන් නැ මුන් මාලනි පොන්සේක කියල.","author":"Purna Alwis","likeCount":12,"totalReplyCount":0,"publishedAt":"2019-02-17T20:43:34.000Z","replies":[]},{"id":"UgxIgI9qIP-gbTFTALl4AaABAg","comment":"කකුලක් දැක්කත් ලංකාවේ උන්ට නිරුවත","author":"Chandani Fernando","likeCount":1,"totalReplyCount":0,"publishedAt":"2019-02-04T21:09:54.000Z","replies":[]},{"id":"UgyHfbyOX2i27DG6VRd4AaABAg","comment":"මුන් නිළියොද බං😂🔫","author":"Ravindu Wanigasooriya","likeCount":6,"totalReplyCount":1,"publishedAt":"2019-02-02T00:40:12.000Z","replies":[{"parentId":"UgyHfbyOX2i27DG6VRd4AaABAg","authorDisplayName":"gayantha kavinda","replyComment":"Podi ekatawath inna denne nathi piumi. Mun niliyoda pkyo","publishedAt":"2019-09-16T16:12:27.000Z","likeCount":0}]},{"id":"Ugy8cZBkOO6sS5IzrQF4AaABAg","comment":"Ko hasini","author":"Sachith Kavishka","likeCount":0,"totalReplyCount":0,"publishedAt":"2019-01-31T14:34:30.000Z","replies":[]},{"id":"UgxlvzsTbjJxm3jlJwd4AaABAg","comment":"කැමති අය යයි.සල්ලිවලට කරන්ක දෙයක් නැතිය.අපි  ගරහන්න හොද නැ.හැදෙන අය මේව බලලා හැදෙයි","author":"Priyantha Priyantha","likeCount":5,"totalReplyCount":0,"publishedAt":"2019-01-28T11:01:24.000Z","replies":[]},{"id":"Ugy6TlQWmX17ti6fBdx4AaABAg","comment":"Wesa badu nudaking rata vinasa wenna topi nisa wesa video dala nudaking huttiyo tawa tika kalaking ballaakwat hukan na topita huhhh","author":"Mohomad Wickram","likeCount":1,"totalReplyCount":0,"publishedAt":"2019-01-25T15:07:29.000Z","replies":[]},{"id":"UgwHhIiF2bqTHcA_G3R4AaABAg","comment":"ammo mun me salli salli manaw kallanwada manda","author":"Sadasi Madud","likeCount":0,"totalReplyCount":1,"publishedAt":"2019-01-25T13:07:18.000Z","replies":[{"parentId":"UgwHhIiF2bqTHcA_G3R4AaABAg","authorDisplayName":"Gamini Damith","replyComment":"Beeg","publishedAt":"2019-07-10T09:06:30.000Z","likeCount":0}]},{"id":"UgwQcNX3hm_xX-qsfnF4AaABAg","comment":"Munta makapa nattana kakakoo wagaa tamaa","author":"priyanthi ariyarathna","likeCount":0,"totalReplyCount":0,"publishedAt":"2019-01-24T15:03:08.000Z","replies":[]},{"id":"UgzF9mTPuJiXJFjzTr94AaABAg","comment":"Nodaka neruwatha raga pana ganu me","author":"Saduni saduni","likeCount":1,"totalReplyCount":1,"publishedAt":"2019-01-22T13:22:21.000Z","replies":[{"parentId":"UgzF9mTPuJiXJFjzTr94AaABAg","authorDisplayName":"Sajith Premananda","replyComment":"Saduni saduni  0713661415 imo","publishedAt":"2019-03-14T03:40:58.000Z","likeCount":0}]},{"id":"UgxqM8wtdtfemRDjRKp4AaABAg","comment":"Kohoma janappriua unath vadak naha lassanai   kiuala    agea   adumath   nathuwa   mona   silpiniuoda","author":"Rays Lankaer","likeCount":0,"totalReplyCount":0,"publishedAt":"2019-01-21T17:28:23.000Z","replies":[]},{"id":"Ugzz4TW7E-x_J9bJU2Z4AaABAg","comment":"Ballo nokhana salli chik","author":"Aisha Deen","likeCount":1,"totalReplyCount":0,"publishedAt":"2019-01-17T12:03:10.000Z","replies":[]},{"id":"UgxiaevhkhAylpX93Mt4AaABAg","comment":"Peti beela sudu wechcha ganikawiyo","author":"Sri lanka Qwer","likeCount":1,"totalReplyCount":0,"publishedAt":"2019-01-16T23:24:27.000Z","replies":[]},{"id":"UgzPtRxsT6R1f29jWZ54AaABAg","comment":"Maranakota  සල්ලි   ganiyanna  puka  pannala  ගන්න   සල්ලි   wadak  na","author":"Shimon Asulin","likeCount":0,"totalReplyCount":0,"publishedAt":"2019-01-13T16:48:48.000Z","replies":[]},{"id":"UgyeSSepHLUQvogBcDN4AaABAg","comment":"Niliyo nemei me ganikawone","author":"Sansala Dewmini","likeCount":2,"totalReplyCount":0,"publishedAt":"2019-01-13T02:18:40.000Z","replies":[]},{"id":"UgyqB2UoUbYDnOtWxnB4AaABAg","comment":"Okkm iraj neh krla thiyene\n.🤣🤣🤣🤣🤣🤣....","author":"Waruni Weerasinghe","likeCount":0,"totalReplyCount":0,"publishedAt":"2019-01-11T03:59:55.000Z","replies":[]},{"id":"Ugzo-DlFm4GFaUbl1zF4AaABAg","comment":"හුත්තන් පෙන්නයි ලෝකෙටම තව ටික දවසකින් සල්ලි නිසා","author":"ඕනි එකක්","likeCount":12,"totalReplyCount":0,"publishedAt":"2019-01-11T01:51:52.000Z","replies":[]},{"id":"Ugx1bJYbuB77LeAKZLh4AaABAg","comment":"කොච්චර සල්ලි හෙව්වත් මොකටද නිරුවත ලෝකෙට පෙන්වලා","author":"Fathima Nafla","likeCount":39,"totalReplyCount":2,"publishedAt":"2019-01-08T12:58:21.000Z","replies":[{"parentId":"Ugx1bJYbuB77LeAKZLh4AaABAg","authorDisplayName":"MG Suraweera","replyComment":"N","publishedAt":"2019-11-30T08:40:20.000Z","likeCount":0},{"parentId":"Ugx1bJYbuB77LeAKZLh4AaABAg","authorDisplayName":"Kithsiri Vikramaarachchi","replyComment":"Fathima Na f la","publishedAt":"2019-02-10T18:29:01.000Z","likeCount":0}]},{"id":"UgyI9kkyQLxrSMn_IkR4AaABAg","comment":"Boru okun owata enne kidenekta lingika allasa dilada","author":"Hema Jayantha","likeCount":0,"totalReplyCount":0,"publishedAt":"2019-01-04T01:13:51.000Z","replies":[]},{"id":"UgyTz8r2-jRV9rdDCth4AaABAg","comment":"wesiyo","author":"Shihara Vimukthi","likeCount":0,"totalReplyCount":0,"publishedAt":"2018-12-31T16:41:19.000Z","replies":[]},{"id":"Ugz-iakavdnjRDmz_Gt4AaABAg","comment":"oya okotama wadiya wesi piumi shinayaka","author":"Lakshan LIyanage","likeCount":0,"totalReplyCount":0,"publishedAt":"2018-12-30T23:49:45.000Z","replies":[]},{"id":"UgwToXH0oC2vhXvus8l4AaABAg","comment":"Me okkama badune dan koheda niliyo inne me okkama badu tika thamai run wenne hina yanawa haloo","author":"Tharanga Perera","likeCount":0,"totalReplyCount":1,"publishedAt":"2018-12-27T06:17:01.000Z","replies":[{"parentId":"UgwToXH0oC2vhXvus8l4AaABAg","authorDisplayName":"pasindu lakshan","replyComment":"Tharanga Perera 😜😜😜😜","publishedAt":"2019-04-17T13:13:35.000Z","likeCount":0}]},{"id":"Ugwsi3pFM1LbuCTDAAB4AaABAg","comment":"Mun okkoma ganu una apitath lajjawak","author":"shashika sewwandi","likeCount":2,"totalReplyCount":4,"publishedAt":"2018-12-24T17:43:29.000Z","replies":[{"parentId":"Ugwsi3pFM1LbuCTDAAB4AaABAg","authorDisplayName":"Sajith Premananda","replyComment":"shashika sewwandi  o71 3661415 imo","publishedAt":"2019-03-14T03:43:37.000Z","likeCount":0},{"parentId":"Ugwsi3pFM1LbuCTDAAB4AaABAg","authorDisplayName":"Naja Ansari","replyComment":"ow ane","publishedAt":"2019-01-11T02:08:07.000Z","likeCount":0},{"parentId":"Ugwsi3pFM1LbuCTDAAB4AaABAg","authorDisplayName":"Maithree Bandara","replyComment":"shashika sewwandi","publishedAt":"2019-01-05T20:04:14.000Z","likeCount":0},{"parentId":"Ugwsi3pFM1LbuCTDAAB4AaABAg","authorDisplayName":"Tissa Jayarathna","replyComment":"Samahara wita monawado wage neda","publishedAt":"2019-01-05T12:00:44.000Z","likeCount":0}]},{"id":"UgzufkSlSd4sAZAF5gB4AaABAg","comment":"98709854 imo kuwet","author":"Wasantha G","likeCount":0,"totalReplyCount":0,"publishedAt":"2018-12-24T05:38:31.000Z","replies":[]},{"id":"Ugznzbd1a1XhOHlRMjp4AaABAg","comment":"Udatai.. Yatatai pinsidda wenna mun ithin hambakaragannawa. Oya dakama han gahila akilunama munta hambakaragannath beri wenawane. Damma karagaththu dayak thama ithin","author":"anusha hettiarachchi anusha","likeCount":0,"totalReplyCount":0,"publishedAt":"2018-12-20T15:21:55.000Z","replies":[]},{"id":"Ugw-hFhPapopdP_4ipt4AaABAg","comment":"Godakma irajge badu","author":"M . S Paranawithana","likeCount":2,"totalReplyCount":0,"publishedAt":"2018-12-19T19:53:08.000Z","replies":[]},{"id":"Ugz3i0F0wf4SNs68cP14AaABAg","comment":"hi","author":"Wasantha Wasantha","likeCount":0,"totalReplyCount":0,"publishedAt":"2018-12-19T17:07:59.000Z","replies":[]},{"id":"UgxykaP9HrBMBqssmLN4AaABAg","comment":"මේගොල්ලන්ට නිළියන් වෙන්න තියෙන ශිල්පීය වටිනාකම මොකක්ද?මේගොල්ලො රූපණය හදාරපු අයද?මෙච්චර ගාණක් අය කරන්න.","author":"Nimsara Ekanayake","likeCount":1,"totalReplyCount":2,"publishedAt":"2018-12-18T18:34:51.000Z","replies":[{"parentId":"UgxykaP9HrBMBqssmLN4AaABAg","authorDisplayName":"Dinu Sumeda","replyComment":"Mata hithena vidihata nam niruwath Penna na darshana thiyenna nisa wenna ethi.gana wedi.mokada wena niliyo wage darshana thiyenna kota enna kemethi nene.sunny lio wage thamai meyalath.","publishedAt":"2019-07-21T13:03:33.000Z","likeCount":0},{"parentId":"UgxykaP9HrBMBqssmLN4AaABAg","authorDisplayName":"Sajith Premananda","replyComment":"Nimsara Ekanayake 0713661416 imo","publishedAt":"2019-03-14T03:41:35.000Z","likeCount":0}]},{"id":"UgzWVkwqPe8fZC3noDN4AaABAg","comment":"ganikawo","author":"Anu Noorjaha","likeCount":0,"totalReplyCount":0,"publishedAt":"2018-12-08T06:26:34.000Z","replies":[]},{"id":"UgxH_g7AlMmuE0uh0nJ4AaABAg","comment":"මේ ලයිසන් තියෙන ගනිකාවොද...?\n(වේසියෝ)","author":"We Are Puttalam පුත්තලමේ අපි","likeCount":4,"totalReplyCount":2,"publishedAt":"2018-12-07T17:42:43.000Z","replies":[{"parentId":"UgxH_g7AlMmuE0uh0nJ4AaABAg","authorDisplayName":"We Are Puttalam පුත්තලමේ අපි","replyComment":"@Kanapathi Kanapathi \n. ........ .?","publishedAt":"2019-01-01T06:02:14.000Z","likeCount":0},{"parentId":"UgxH_g7AlMmuE0uh0nJ4AaABAg","authorDisplayName":"Kanapathi Kanapathi","replyComment":"Amila Prashan u","publishedAt":"2018-12-31T17:37:59.000Z","likeCount":1}]},{"id":"Ugx5TIifccLEfeDDPQV4AaABAg","comment":"ඔක්කොම කැරි බඩු 😂😂","author":"Sahan Prabashwara","likeCount":8,"totalReplyCount":0,"publishedAt":"2018-12-01T02:34:43.000Z","replies":[]},{"id":"UgxpVF13oBlZIsW4hPR4AaABAg","comment":"Maru okkoma badu.","author":"Chanaka Suresh","likeCount":1,"totalReplyCount":0,"publishedAt":"2018-11-25T04:34:51.000Z","replies":[]},{"id":"UgyLBw7qF68yrKAJk7V4AaABAg","comment":"mun niyoda ban..meta wada hodata ragapanwa dewmi...","author":"Kavindi Gayani","likeCount":2,"totalReplyCount":3,"publishedAt":"2018-11-24T23:43:00.000Z","replies":[{"parentId":"UgyLBw7qF68yrKAJk7V4AaABAg","authorDisplayName":"Sajith Premananda","replyComment":"Kavindi Gayani o713661415 imo","publishedAt":"2019-03-14T03:42:48.000Z","likeCount":0},{"parentId":"UgyLBw7qF68yrKAJk7V4AaABAg","authorDisplayName":"Wasantha Wasantha","replyComment":"kohomada oyata","publishedAt":"2018-12-09T22:18:03.000Z","likeCount":0},{"parentId":"UgyLBw7qF68yrKAJk7V4AaABAg","authorDisplayName":"Wasantha Wasantha","replyComment":"hmmmm kohomada","publishedAt":"2018-12-09T22:12:18.000Z","likeCount":0}]},{"id":"Ugyy-g9dhdg_1j8xvsB4AaABAg","comment":"Supri kali  bn matath asai","author":"Ruwan Mobile","likeCount":0,"totalReplyCount":0,"publishedAt":"2018-11-23T16:49:54.000Z","replies":[]},{"id":"UgyBgddOWvUQmoiZwqJ4AaABAg","comment":"Supri","author":"Ruwan Mobile","likeCount":0,"totalReplyCount":0,"publishedAt":"2018-11-23T16:47:14.000Z","replies":[]},{"id":"Ugx_nKpXiC63dNxX0e54AaABAg","comment":"Pala yako boru nokiya..","author":"Nipun Madushan","likeCount":6,"totalReplyCount":0,"publishedAt":"2018-11-19T18:21:23.000Z","replies":[]},{"id":"UgwkSD95TEIpXlayJ6Z4AaABAg","comment":"0762249293","author":"Gayan Chathuranga","likeCount":0,"totalReplyCount":0,"publishedAt":"2018-11-19T03:19:09.000Z","replies":[]},{"id":"UgzrEp6JprN-F9QX43V4AaABAg","comment":"How much do they charge for one night fucking?\nALL BLOODY BITCHES.","author":"Dad Somaweera","likeCount":0,"totalReplyCount":0,"publishedAt":"2018-11-18T08:53:59.000Z","replies":[]},{"id":"UgxCm5ePukWizE7aXhF4AaABAg","comment":"0775712073imo","author":"Gayan tharanga","likeCount":0,"totalReplyCount":0,"publishedAt":"2018-11-15T18:35:41.000Z","replies":[]},{"id":"UgyvE7xCa2xttxjgoK54AaABAg","comment":"tamangea leabima","author":"Dinu adareai wastu","likeCount":0,"totalReplyCount":0,"publishedAt":"2018-11-03T17:58:06.000Z","replies":[]},{"id":"Ugxvn8YLHZMT9adlsDp4AaABAg","comment":"me aiye... meyalata gahanda kiyada kiyalat dapanko ban","author":"Ravindu Madhawa","likeCount":0,"totalReplyCount":0,"publishedAt":"2018-10-12T14:21:59.000Z","replies":[]},{"id":"UgzMwS2_crIz29R36-p4AaABAg","comment":"Mun wesiyone","author":"Priyanka Priyanka","likeCount":0,"totalReplyCount":0,"publishedAt":"2018-10-11T20:48:55.000Z","replies":[]},{"id":"Ugwlcuzf3luUCBhDUzZ4AaABAg","comment":"munwa form karanawane,netuwa munwa Rs.500kwat watinne","author":"Piumi 1234","likeCount":1,"totalReplyCount":1,"publishedAt":"2018-09-16T16:43:09.000Z","replies":[{"parentId":"Ugwlcuzf3luUCBhDUzZ4AaABAg","authorDisplayName":"Wasantha Wasantha","replyComment":"HMM","publishedAt":"2018-11-19T15:57:54.000Z","likeCount":0}]},{"id":"UgyWKn8RD8-bflTEYQJ4AaABAg","comment":"වෙිසා බඩු","author":"Meethiya Milinda","likeCount":1,"totalReplyCount":1,"publishedAt":"2018-09-12T14:34:37.000Z","replies":[{"parentId":"UgyWKn8RD8-bflTEYQJ4AaABAg","authorDisplayName":"Sajith Premananda","replyComment":"Meethiya Milinda 0713661415 imo","publishedAt":"2019-03-14T03:44:31.000Z","likeCount":0}]},{"id":"UgyNv1CGs8SB5R4zYDB4AaABAg","comment":"Owa balana unta gahanna ona","author":"hiru Kanchana","likeCount":0,"totalReplyCount":0,"publishedAt":"2018-07-05T20:31:40.000Z","replies":[]},{"id":"Ugwul8fHf2hPvW98i3B4AaABAg","comment":"Hokagana kiyak kiyaida","author":"Daham dildara","likeCount":0,"totalReplyCount":0,"publishedAt":"2018-07-04T17:44:20.000Z","replies":[]},{"id":"Ugwp-Ge2rjISVrQIONp4AaABAg","comment":"Apooo okkomaa hoda na  kochchara salli hamba karath wedakk naa hadiyawak naththammm broooo","author":"Dewindi Kaushalya","likeCount":8,"totalReplyCount":3,"publishedAt":"2018-06-17T10:32:21.000Z","replies":[{"parentId":"Ugwp-Ge2rjISVrQIONp4AaABAg","authorDisplayName":"Sajith Premananda","replyComment":"Dewindi Kaushalya  0713661415 imo","publishedAt":"2019-03-14T03:40:09.000Z","likeCount":0},{"parentId":"Ugwp-Ge2rjISVrQIONp4AaABAg","authorDisplayName":"Susantha Premalal","replyComment":"Mokadda hadiyawai oyawadai atara wanasa","publishedAt":"2018-10-31T18:41:51.000Z","likeCount":0}]},{"id":"UgxtUJKjxSPlqiZV78J4AaABAg","comment":"Puka dela Hari Wade karaganilla   kohomath akane wenne neda wasthula gewal wahana gannath oni neda kukku  ammilataaa ithin pukatikak dela wede karagannawa munge  huththawal walata wada  galdekata wada ape game wawen Nala  deyaredda adagana godata Ana kusumakka lassai","author":"Sajith sajith","likeCount":4,"totalReplyCount":0,"publishedAt":"2018-05-28T23:22:38.000Z","replies":[]},{"id":"UgywJk2j1wne0yz0vLt4AaABAg","comment":"Yako mevage vesiyo Gena dala ape age le puchchanne nethuva Hoda  deyak dahallako ban  ubalanam aneee chiiiiiiii......","author":"nethu lanka","likeCount":0,"totalReplyCount":0,"publishedAt":"2018-05-18T11:49:11.000Z","replies":[]},{"id":"Ugzq1p1DOqfEwP4RXox4AaABAg","comment":"Iraj vage ponna pakayekta mevage Gon Badu Hoda athi apitanam chik Pau appa salli.  ......","author":"nethu lanka","likeCount":0,"totalReplyCount":0,"publishedAt":"2018-05-18T11:46:31.000Z","replies":[]},{"id":"Ugx0rw7dmr4oQkq443R4AaABAg","comment":"mokada eyalage wesakama wadi venna venna hila loku wenna wenna gaanath wadi wenawada.muntika niliyoda. mun patta gonnune.","author":"Ds Subashana","likeCount":5,"totalReplyCount":1,"publishedAt":"2018-05-17T06:51:54.000Z","replies":[{"parentId":"Ugx0rw7dmr4oQkq443R4AaABAg","authorDisplayName":"Siraj Wahid","replyComment":"Ds Subashana","publishedAt":"2018-05-18T02:59:18.000Z","likeCount":0}]},{"id":"UgwO4tLFM6Si7xwhvCd4AaABAg","comment":"අපිට මොකෝ.ඔක්කොම එකයි","author":"Nisansalasewwandi Ns","likeCount":4,"totalReplyCount":0,"publishedAt":"2018-05-16T04:07:26.000Z","replies":[]},{"id":"UgzoYp_RF0wTmlBVBNJ4AaABAg","comment":"Mun badune araka vikunala eaita wada gannawane  iraj gahapu gahillta iraj hoyagena piumi yanne pukata gahuwoth pai kota watenawa 100 vithara","author":"Saman Saman","likeCount":4,"totalReplyCount":0,"publishedAt":"2018-05-15T12:18:27.000Z","replies":[]},{"id":"UgwtY8rA_Izozu3EKaJ4AaABAg","comment":"Mun mona niliyoda.  Munta niliyo kiyana outa pissu","author":"ron Iddamalgoda","likeCount":6,"totalReplyCount":1,"publishedAt":"2018-05-14T02:47:36.000Z","replies":[{"parentId":"UgwtY8rA_Izozu3EKaJ4AaABAg","authorDisplayName":"චාමර ගුණවර්ධන.","replyComment":"ron Iddamalgoda mama oyawa sub kara mawath sub karanna","publishedAt":"2018-07-25T06:48:21.000Z","likeCount":0}]},{"id":"Ugz0Iu9MMMjbw8aQMr94AaABAg","comment":"e rangapana hetiyata salli godak oni thamai","author":"shani wijesinghe shani wijesinghe","likeCount":0,"totalReplyCount":0,"publishedAt":"2018-05-12T09:17:56.000Z","replies":[]},{"id":"UgztVqmuXJMWR7gpInV4AaABAg","comment":"eta wada ganwane dila","author":"Mihidum Max","likeCount":0,"totalReplyCount":1,"publishedAt":"2018-05-11T10:23:52.000Z","replies":[{"parentId":"UgztVqmuXJMWR7gpInV4AaABAg","authorDisplayName":"kumari විජේපාල","replyComment":"Jara genune","publishedAt":"2019-01-26T11:17:46.000Z","likeCount":0}]},{"id":"UgwvcW6acSa8q50gSAt4AaABAg","comment":"ai  ma  wasiyo  hodata  palal  karanawada . munta moona  hodan  anda  kiyahan balanda  ballo  bat  kanat na.palayan gampalatata lassana  kallo  balanda anit   lassan kallantat apahasayak","author":"Gayan Sameera","likeCount":3,"totalReplyCount":0,"publishedAt":"2018-05-05T18:11:02.000Z","replies":[]},{"id":"Ugx5tBmsaRZeQF3ltSd4AaABAg","comment":"මතු උපදින කිසිම භවයකදී මෙවැනි රටක ඉපදීමට නොපතන්නේය.\nඇයි එහෙම කියන්නේ,\nහාමුදුරුවරුයයි කියාගන්නා, බුදුන්ගේ වචනයට හාත්පසින්ම වෙනස්වූ ආකාරයට දිවිපෙවත ගතකරන \nපල්හොරුන්ට දැන හෝ නොදැන සංග්‍රහ කිරීමට බැරිය.\nතම තමන්ගේ පවුල් පමණක් ආරක්ෂා කිරීමට ක්‍රියාකරන හොර දේශපාලුවන්ට යටත්ව ජීවත්වීමට බැරිය.\nමැරෙන තුරු ක්‍රෝධයෙන් ජීවත්වෙන මිනිසුන් ආශ්‍රය කිරීමට බැරිය.\nකවුරු පාලනය කරත් රට කරවන හැටි බලාගෙන මුළු ශරීරයේම අංශු තදවීම, තෙරපීම, රත්වීම සහ දෙදරීමට යටත් වීමට ඉඩදිය නොහැක.    \nමේ සමහරක් හේතූන් පමණකි. තව බොහෝ ඇත,","author":"andana nandana","likeCount":5,"totalReplyCount":1,"publishedAt":"2018-04-29T08:42:15.000Z","replies":[{"parentId":"Ugx5tBmsaRZeQF3ltSd4AaABAg","authorDisplayName":"sunil rajapaksha","replyComment":"andana nandana  oba hari meratata budun wediyeth weradila wenna one gauthama budun ada hitiyansm monatharam dukweida sasanayath iwarai ratath iwarai ada siuru porava gaththu horu ematai","publishedAt":"2018-07-02T20:37:40.000Z","likeCount":0}]},{"id":"UgzmdwTgvkLBUiTAiEV4AaABAg","comment":"Can you post one photo without make-ups from all of them","author":"Enoka Mannaperuma","likeCount":2,"totalReplyCount":0,"publishedAt":"2018-03-29T16:33:49.000Z","replies":[]},{"id":"UgxaxlhWXH80K7s9jVZ4AaABAg","comment":"හොදයි නේ වීඩියෝ 5-6ක් කර ගත්තම","author":"Morayez Entertainment","likeCount":6,"totalReplyCount":6,"publishedAt":"2018-03-28T19:37:08.000Z","replies":[{"parentId":"UgxaxlhWXH80K7s9jVZ4AaABAg","authorDisplayName":"Sajith Premananda","replyComment":"දයාබර නෙතූ 0713661415 imo","publishedAt":"2019-03-14T03:42:19.000Z","likeCount":0},{"parentId":"UgxaxlhWXH80K7s9jVZ4AaABAg","authorDisplayName":"Kelum Thushara","replyComment":"Nxxxxethu Gamage","publishedAt":"2018-12-22T17:17:37.000Z","likeCount":0},{"parentId":"UgxaxlhWXH80K7s9jVZ4AaABAg","authorDisplayName":"Sachintha Madumadawa","replyComment":"Nethu Gamage","publishedAt":"2018-12-12T18:29:33.000Z","likeCount":0},{"parentId":"UgxaxlhWXH80K7s9jVZ4AaABAg","authorDisplayName":"Senevirathna Bandara","replyComment":"Nethu Gamage uhgyýgy","publishedAt":"2018-12-09T21:54:57.000Z","likeCount":0},{"parentId":"UgxaxlhWXH80K7s9jVZ4AaABAg","authorDisplayName":"Susantha Premalal","replyComment":"Video akak dala ai oya baluva nadda","publishedAt":"2018-10-31T18:39:12.000Z","likeCount":1},{"parentId":"UgxaxlhWXH80K7s9jVZ4AaABAg","authorDisplayName":"චාමර ගුණවර්ධන.","replyComment":"N.sahiree Reanuka Gamage mama oyawa sub kara mawath sub karanna","publishedAt":"2018-07-25T06:49:43.000Z","likeCount":0}]},{"id":"UgzFEtfWdVGDU4OOlit4AaABAg","comment":"ඔක්කමවෙිසියෙ","author":"Widanage Ravi","likeCount":32,"totalReplyCount":1,"publishedAt":"2018-03-28T09:36:04.000Z","replies":[{"parentId":"UgzFEtfWdVGDU4OOlit4AaABAg","authorDisplayName":"Priyantha Karunarathne","replyComment":"Widanage Ravi dfhhihvccxdthihhbf","publishedAt":"2018-05-11T16:26:56.000Z","likeCount":0}]},{"id":"UgxckbneGQqfuu4j1f94AaABAg","comment":"Me ganu dakkamath appiriyai.niliyanta apahasa karanna epa mun niliyoda.","author":"Aruna Thenuwara","likeCount":11,"totalReplyCount":1,"publishedAt":"2018-03-27T19:10:07.000Z","replies":[{"parentId":"UgxckbneGQqfuu4j1f94AaABAg","authorDisplayName":"Jayasiri Jayasiri","replyComment":"Beegnbeeg","publishedAt":"2019-05-18T17:25:24.000Z","likeCount":0}]},{"id":"UgziB4f7IoctBJmYocF4AaABAg","comment":"Mun nilyo nemi hodama wishiyo.ganikawo lankawi inna munta.kauruth kamathi nee wasiyoo","author":"Kumari Perera","likeCount":5,"totalReplyCount":1,"publishedAt":"2018-03-27T18:31:46.000Z","replies":[{"parentId":"UgziB4f7IoctBJmYocF4AaABAg","authorDisplayName":"චාමර ගුණවර්ධන.","replyComment":"Kumari Perera mama oyawa sub kara mawath sub karanna","publishedAt":"2018-07-25T06:48:37.000Z","likeCount":1}]},{"id":"UgyIu8VCtOYoT_KDQyx4AaABAg","comment":"☺️☺️☺️☺️☺️","author":"Hima ranu","likeCount":2,"totalReplyCount":2,"publishedAt":"2018-03-27T16:08:36.000Z","replies":[{"parentId":"UgyIu8VCtOYoT_KDQyx4AaABAg","authorDisplayName":"චාමර ගුණවර්ධන.","replyComment":"Hima ranu mama oyawa sub kara mawath sub karanna","publishedAt":"2018-07-25T06:49:09.000Z","likeCount":0},{"parentId":"UgyIu8VCtOYoT_KDQyx4AaABAg","authorDisplayName":"Harshani Mangalika","replyComment":"patta","publishedAt":"2018-04-18T02:08:19.000Z","likeCount":0}]}]}]